{"ekdv-060":"en/ek/dv/-0/en-ekdv-060.html","ec-085":"en/ec/-0/85/en-ec-085.html","evo-103":"en/ev/o-/10/en-evo-103.html","evo-104":"en/ev/o-/10/en-evo-104.html","ezd-293":"en/ez/d-/29/en-ezd-293.html","ezd-292":"en/ez/d-/29/en-ezd-292.html","ezd-291":"en/ez/d-/29/en-ezd-291.html","emrd-004":"en/em/rd/-0/en-emrd-004.html","emau-005":"en/em/au/-0/en-emau-005.html","emrd-003":"en/em/rd/-0/en-emrd-003.html","emau-004":"en/em/au/-0/en-emau-004.html","elo-248":"en/el/o-/24/en-elo-248.html","elo-244":"en/el/o-/24/en-elo-244.html","elo-247":"en/el/o-/24/en-elo-247.html","egt-005":"en/eg/t-/00/en-egt-005.html","ezd-295":"en/ez/d-/29/en-ezd-295.html","ezd-294":"en/ez/d-/29/en-ezd-294.html","ebod-088":"en/eb/od/-0/en-ebod-088.html","ebod-090":"en/eb/od/-0/en-ebod-090.html","ebod-089":"en/eb/od/-0/en-ebod-089.html","ezd-288":"en/ez/d-/28/en-ezd-288.html","ezd-289":"en/ez/d-/28/en-ezd-289.html","ezd-287":"en/ez/d-/28/en-ezd-287.html","ezd-286":"en/ez/d-/28/en-ezd-286.html","ezd-290":"en/ez/d-/29/en-ezd-290.html","ecb-039":"en/ec/b-/03/en-ecb-039.html","emaz-026":"en/em/az/-0/en-emaz-026.html","emaz-025":"en/em/az/-0/en-emaz-025.html","emaz-027":"en/em/az/-0/en-emaz-027.html","emau-003":"en/em/au/-0/en-emau-003.html","emau-001":"en/em/au/-0/en-emau-001.html","emau-002":"en/em/au/-0/en-emau-002.html","emaf-021":"en/em/af/-0/en-emaf-021.html","emas-015":"en/em/as/-0/en-emas-015.html","emas-013":"en/em/as/-0/en-emas-013.html","emaf-018":"en/em/af/-0/en-emaf-018.html","emaf-019":"en/em/af/-0/en-emaf-019.html","emaf-020":"en/em/af/-0/en-emaf-020.html","edgd-177":"en/ed/gd/-1/en-edgd-177.html","edgd-176":"en/ed/gd/-1/en-edgd-176.html","edgd-175":"en/ed/gd/-1/en-edgd-175.html","ezd-285":"en/ez/d-/28/en-ezd-285.html","evo-099":"en/ev/o-/09/en-evo-099.html","ezd-284":"en/ez/d-/28/en-ezd-284.html","edd-163":"en/ed/d-/16/en-edd-163.html","egt-004":"en/eg/t-/00/en-egt-004.html","egt-003":"en/eg/t-/00/en-egt-003.html","edd-162":"en/ed/d-/16/en-edd-162.html","emu-054":"en/em/u-/05/en-emu-054.html","ec-084":"en/ec/-0/84/en-ec-084.html","ekdv-057":"en/ek/dv/-0/en-ekdv-057.html","ezd-281":"en/ez/d-/28/en-ezd-281.html","ekdv-056":"en/ek/dv/-0/en-ekdv-056.html","evo-098":"en/ev/o-/09/en-evo-098.html","evo-097":"en/ev/o-/09/en-evo-097.html","ezd-279":"en/ez/d-/27/en-ezd-279.html","ezd-280":"en/ez/d-/28/en-ezd-280.html","ezd-282":"en/ez/d-/28/en-ezd-282.html","ezd-283":"en/ez/d-/28/en-ezd-283.html","enkd-002":"en/en/kd/-0/en-enkd-002.html","enkd-001":"en/en/kd/-0/en-enkd-001.html","elo-239":"en/el/o-/23/en-elo-239.html","emaz-024":"en/em/az/-0/en-emaz-024.html","emrd-002":"en/em/rd/-0/en-emrd-002.html","emaz-023":"en/em/az/-0/en-emaz-023.html","elo-243":"en/el/o-/24/en-elo-243.html","elo-242":"en/el/o-/24/en-elo-242.html","elo-240":"en/el/o-/24/en-elo-240.html","elo-241":"en/el/o-/24/en-elo-241.html","ec-073":"en/ec/-0/73/en-ec-073.html","ebod-086":"en/eb/od/-0/en-ebod-086.html","ebod-085":"en/eb/od/-0/en-ebod-085.html","ebod-087":"en/eb/od/-0/en-ebod-087.html","ezd-278":"en/ez/d-/27/en-ezd-278.html","ezd-277":"en/ez/d-/27/en-ezd-277.html","ezd-275":"en/ez/d-/27/en-ezd-275.html","ezd-276":"en/ez/d-/27/en-ezd-276.html","ezd-274":"en/ez/d-/27/en-ezd-274.html","ezd-273":"en/ez/d-/27/en-ezd-273.html","ezd-268":"en/ez/d-/26/en-ezd-268.html","ekdv-054":"en/ek/dv/-0/en-ekdv-054.html","ecb-038":"en/ec/b-/03/en-ecb-038.html","ezd-271":"en/ez/d-/27/en-ezd-271.html","ezd-272":"en/ez/d-/27/en-ezd-272.html","edd-160":"en/ed/d-/16/en-edd-160.html","ezd-269":"en/ez/d-/26/en-ezd-269.html","edd-161":"en/ed/d-/16/en-edd-161.html","ezd-267":"en/ez/d-/26/en-ezd-267.html","egt-002":"en/eg/t-/00/en-egt-002.html","emas-012":"en/em/as/-0/en-emas-012.html","edgd-173":"en/ed/gd/-1/en-edgd-173.html","emaz-022":"en/em/az/-0/en-emaz-022.html","emaf-017":"en/em/af/-0/en-emaf-017.html","emaz-020":"en/em/az/-0/en-emaz-020.html","emaz-019":"en/em/az/-0/en-emaz-019.html","emaf-015":"en/em/af/-0/en-emaf-015.html","emad-007":"en/em/ad/-0/en-emad-007.html","emaf-016":"en/em/af/-0/en-emaf-016.html","ec-083":"en/ec/-0/83/en-ec-083.html","exe-035":"en/ex/e-/03/en-exe-035.html","exe-043":"en/ex/e-/04/en-exe-043.html","ekdv-052":"en/ek/dv/-0/en-ekdv-052.html","evo-094":"en/ev/o-/09/en-evo-094.html","evo-093":"en/ev/o-/09/en-evo-093.html","ezd-266":"en/ez/d-/26/en-ezd-266.html","egt-001":"en/eg/t-/00/en-egt-001.html","elo-238":"en/el/o-/23/en-elo-238.html","elo-237":"en/el/o-/23/en-elo-237.html","elo-235":"en/el/o-/23/en-elo-235.html","elo-234":"en/el/o-/23/en-elo-234.html","elo-236":"en/el/o-/23/en-elo-236.html","eight-122":"en/ei/gh/t-/en-eight-122.html","ekdv-050":"en/ek/dv/-0/en-ekdv-050.html","ekdv-051":"en/ek/dv/-0/en-ekdv-051.html","ebod-081":"en/eb/od/-0/en-ebod-081.html","ebod-083":"en/eb/od/-0/en-ebod-083.html","ebod-084":"en/eb/od/-0/en-ebod-084.html","ebod-082":"en/eb/od/-0/en-ebod-082.html","ezd-262":"en/ez/d-/26/en-ezd-262.html","ezd-263":"en/ez/d-/26/en-ezd-263.html","ezd-261":"en/ez/d-/26/en-ezd-261.html","ezd-264":"en/ez/d-/26/en-ezd-264.html","ezd-265":"en/ez/d-/26/en-ezd-265.html","ecb-037":"en/ec/b-/03/en-ecb-037.html","ezd-259":"en/ez/d-/25/en-ezd-259.html","edd-159":"en/ed/d-/15/en-edd-159.html","edgd-172":"en/ed/gd/-1/en-edgd-172.html","edgd-171":"en/ed/gd/-1/en-edgd-171.html","ezd-258":"en/ez/d-/25/en-ezd-258.html","edd-158":"en/ed/d-/15/en-edd-158.html","ekdv-049":"en/ek/dv/-0/en-ekdv-049.html","emas-009":"en/em/as/-0/en-emas-009.html","emaz-018":"en/em/az/-0/en-emaz-018.html","emaz-017":"en/em/az/-0/en-emaz-017.html","emaz-016":"en/em/az/-0/en-emaz-016.html","emaw-002":"en/em/aw/-0/en-emaw-002.html","emaf-013":"en/em/af/-0/en-emaf-013.html","emas-010":"en/em/as/-0/en-emas-010.html","emas-008":"en/em/as/-0/en-emas-008.html","emad-006":"en/em/ad/-0/en-emad-006.html","emaf-011":"en/em/af/-0/en-emaf-011.html","emu-052":"en/em/u-/05/en-emu-052.html","emu-051":"en/em/u-/05/en-emu-051.html","ec-082":"en/ec/-0/82/en-ec-082.html","emu-050":"en/em/u-/05/en-emu-050.html","evo-090":"en/ev/o-/09/en-evo-090.html","evo-089":"en/ev/o-/08/en-evo-089.html","ezd-256":"en/ez/d-/25/en-ezd-256.html","ezd-255":"en/ez/d-/25/en-ezd-255.html","ezd-257":"en/ez/d-/25/en-ezd-257.html","ekdv-048":"en/ek/dv/-0/en-ekdv-048.html","emrd-001":"en/em/rd/-0/en-emrd-001.html","elo-228":"en/el/o-/22/en-elo-228.html","elo-227":"en/el/o-/22/en-elo-227.html","elo-231":"en/el/o-/23/en-elo-231.html","elo-232":"en/el/o-/23/en-elo-232.html","ekdv-046":"en/ek/dv/-0/en-ekdv-046.html","ebod-078":"en/eb/od/-0/en-ebod-078.html","ebod-079":"en/eb/od/-0/en-ebod-079.html","ezd-251":"en/ez/d-/25/en-ezd-251.html","ezd-248":"en/ez/d-/24/en-ezd-248.html","ezd-254":"en/ez/d-/25/en-ezd-254.html","ezd-250":"en/ez/d-/25/en-ezd-250.html","ezd-252":"en/ez/d-/25/en-ezd-252.html","ezd-253":"en/ez/d-/25/en-ezd-253.html","ecb-036":"en/ec/b-/03/en-ecb-036.html","edd-157":"en/ed/d-/15/en-edd-157.html","ezd-247":"en/ez/d-/24/en-ezd-247.html","etc-012":"en/et/c-/01/en-etc-012.html","ezd-245":"en/ez/d-/24/en-ezd-245.html","edd-156":"en/ed/d-/15/en-edd-156.html","edgd-169":"en/ed/gd/-1/en-edgd-169.html","edgd-170":"en/ed/gd/-1/en-edgd-170.html","ekdv-044":"en/ek/dv/-0/en-ekdv-044.html","emaz-013":"en/em/az/-0/en-emaz-013.html","emaz-014":"en/em/az/-0/en-emaz-014.html","emaz-012":"en/em/az/-0/en-emaz-012.html","emaz-011":"en/em/az/-0/en-emaz-011.html","emas-007":"en/em/as/-0/en-emas-007.html","emaf-009":"en/em/af/-0/en-emaf-009.html","emad-005":"en/em/ad/-0/en-emad-005.html","emam-001":"en/em/am/-0/en-emam-001.html","evo-086":"en/ev/o-/08/en-evo-086.html","ezd-243":"en/ez/d-/24/en-ezd-243.html","evo-085":"en/ev/o-/08/en-evo-085.html","ezd-242":"en/ez/d-/24/en-ezd-242.html","ezd-241":"en/ez/d-/24/en-ezd-241.html","ezd-240":"en/ez/d-/24/en-ezd-240.html","ezd-244":"en/ez/d-/24/en-ezd-244.html","elo-222":"en/el/o-/22/en-elo-222.html","elo-226":"en/el/o-/22/en-elo-226.html","elo-223":"en/el/o-/22/en-elo-223.html","ekdv-045":"en/ek/dv/-0/en-ekdv-045.html","ezd-236":"en/ez/d-/23/en-ezd-236.html","ezd-237":"en/ez/d-/23/en-ezd-237.html","ekdv-043":"en/ek/dv/-0/en-ekdv-043.html","ezd-238":"en/ez/d-/23/en-ezd-238.html","ezd-239":"en/ez/d-/23/en-ezd-239.html","ezd-235":"en/ez/d-/23/en-ezd-235.html","evo-083":"en/ev/o-/08/en-evo-083.html","evo-084":"en/ev/o-/08/en-evo-084.html","ebod-075":"en/eb/od/-0/en-ebod-075.html","ebod-074":"en/eb/od/-0/en-ebod-074.html","ebod-076":"en/eb/od/-0/en-ebod-076.html","ebod-077":"en/eb/od/-0/en-ebod-077.html","ekdv-042":"en/ek/dv/-0/en-ekdv-042.html","ecb-035":"en/ec/b-/03/en-ecb-035.html","ezd-234":"en/ez/d-/23/en-ezd-234.html","edd-155":"en/ed/d-/15/en-edd-155.html","edd-154":"en/ed/d-/15/en-edd-154.html","ezd-233":"en/ez/d-/23/en-ezd-233.html","erh-041":"en/er/h-/04/en-erh-041.html","edgd-168":"en/ed/gd/-1/en-edgd-168.html","edgd-167":"en/ed/gd/-1/en-edgd-167.html","emaz-008":"en/em/az/-0/en-emaz-008.html","emaz-007":"en/em/az/-0/en-emaz-007.html","emas-005":"en/em/as/-0/en-emas-005.html","emas-003":"en/em/as/-0/en-emas-003.html","emas-004":"en/em/as/-0/en-emas-004.html","emad-004":"en/em/ad/-0/en-emad-004.html","emas-001":"en/em/as/-0/en-emas-001.html","emas-002":"en/em/as/-0/en-emas-002.html","ekdv-040":"en/ek/dv/-0/en-ekdv-040.html","evo-082":"en/ev/o-/08/en-evo-082.html","ezd-230":"en/ez/d-/23/en-ezd-230.html","evo-081":"en/ev/o-/08/en-evo-081.html","ezd-226":"en/ez/d-/22/en-ezd-226.html","ezd-229":"en/ez/d-/22/en-ezd-229.html","ezd-227":"en/ez/d-/22/en-ezd-227.html","ezd-228":"en/ez/d-/22/en-ezd-228.html","ezd-231":"en/ez/d-/23/en-ezd-231.html","elo-219":"en/el/o-/21/en-elo-219.html","elo-218":"en/el/o-/21/en-elo-218.html","elo-221":"en/el/o-/22/en-elo-221.html","elo-220":"en/el/o-/22/en-elo-220.html","exe-021":"en/ex/e-/02/en-exe-021.html","ekdv-038":"en/ek/dv/-0/en-ekdv-038.html","ebod-070":"en/eb/od/-0/en-ebod-070.html","ebod-071":"en/eb/od/-0/en-ebod-071.html","erh-031":"en/er/h-/03/en-erh-031.html","ebod-072":"en/eb/od/-0/en-ebod-072.html","erh-030":"en/er/h-/03/en-erh-030.html","erh-034":"en/er/h-/03/en-erh-034.html","ebod-073":"en/eb/od/-0/en-ebod-073.html","ekdv-039":"en/ek/dv/-0/en-ekdv-039.html","ezd-223":"en/ez/d-/22/en-ezd-223.html","ezd-224":"en/ez/d-/22/en-ezd-224.html","ezd-222":"en/ez/d-/22/en-ezd-222.html","ezd-225":"en/ez/d-/22/en-ezd-225.html","ezd-221":"en/ez/d-/22/en-ezd-221.html","erod-081":"en/er/od/-0/en-erod-081.html","ebl-003":"en/eb/l-/00/en-ebl-003.html","erh-025":"en/er/h-/02/en-erh-025.html","edgd-166":"en/ed/gd/-1/en-edgd-166.html","edgd-165":"en/ed/gd/-1/en-edgd-165.html","edd-153":"en/ed/d-/15/en-edd-153.html","ezd-219":"en/ez/d-/21/en-ezd-219.html","edd-152":"en/ed/d-/15/en-edd-152.html","egwx-001":"en/eg/wx/-0/en-egwx-001.html","ekdv-037":"en/ek/dv/-0/en-ekdv-037.html","emaf-005":"en/em/af/-0/en-emaf-005.html","emaz-006":"en/em/az/-0/en-emaz-006.html","evo-078":"en/ev/o-/07/en-evo-078.html","ezd-218":"en/ez/d-/21/en-ezd-218.html","ezd-217":"en/ez/d-/21/en-ezd-217.html","evo-077":"en/ev/o-/07/en-evo-077.html","ekdv-036":"en/ek/dv/-0/en-ekdv-036.html","elo-213":"en/el/o-/21/en-elo-213.html","elo-212":"en/el/o-/21/en-elo-212.html","elo-216":"en/el/o-/21/en-elo-216.html","ekdv-034":"en/ek/dv/-0/en-ekdv-034.html","ekdv-035":"en/ek/dv/-0/en-ekdv-035.html","ebod-069":"en/eb/od/-0/en-ebod-069.html","ebod-068":"en/eb/od/-0/en-ebod-068.html","ezd-210":"en/ez/d-/21/en-ezd-210.html","ezd-212":"en/ez/d-/21/en-ezd-212.html","evo-076":"en/ev/o-/07/en-evo-076.html","ezd-216":"en/ez/d-/21/en-ezd-216.html","ezd-214":"en/ez/d-/21/en-ezd-214.html","ezd-211":"en/ez/d-/21/en-ezd-211.html","ezd-213":"en/ez/d-/21/en-ezd-213.html","evo-075":"en/ev/o-/07/en-evo-075.html","erod-094":"en/er/od/-0/en-erod-094.html","ecb-034":"en/ec/b-/03/en-ecb-034.html","edd-150":"en/ed/d-/15/en-edd-150.html","edd-151":"en/ed/d-/15/en-edd-151.html","esb-019":"en/es/b-/01/en-esb-019.html","esb-020":"en/es/b-/02/en-esb-020.html","ezd-209":"en/ez/d-/20/en-ezd-209.html","edgd-164":"en/ed/gd/-1/en-edgd-164.html","edgd-163":"en/ed/gd/-1/en-edgd-163.html","ekdv-032":"en/ek/dv/-0/en-ekdv-032.html","eight-114":"en/ei/gh/t-/en-eight-114.html","emaz-004":"en/em/az/-0/en-emaz-004.html","emaf-003":"en/em/af/-0/en-emaf-003.html","emad-002":"en/em/ad/-0/en-emad-002.html","evo-073":"en/ev/o-/07/en-evo-073.html","ezd-208":"en/ez/d-/20/en-ezd-208.html","ezd-206":"en/ez/d-/20/en-ezd-206.html","evo-074":"en/ev/o-/07/en-evo-074.html","ezd-207":"en/ez/d-/20/en-ezd-207.html","elo-210":"en/el/o-/21/en-elo-210.html","elo-207":"en/el/o-/20/en-elo-207.html","elo-208":"en/el/o-/20/en-elo-208.html","elo-209":"en/el/o-/20/en-elo-209.html","elo-206":"en/el/o-/20/en-elo-206.html","ekdv-031":"en/ek/dv/-0/en-ekdv-031.html","ebod-066":"en/eb/od/-0/en-ebod-066.html","ebod-065":"en/eb/od/-0/en-ebod-065.html","ebod-067":"en/eb/od/-0/en-ebod-067.html","ekdv-030":"en/ek/dv/-0/en-ekdv-030.html","ezd-204":"en/ez/d-/20/en-ezd-204.html","evo-072":"en/ev/o-/07/en-evo-072.html","ezd-205":"en/ez/d-/20/en-ezd-205.html","ekdv-029":"en/ek/dv/-0/en-ekdv-029.html","ebl-002":"en/eb/l-/00/en-ebl-002.html","ezd-200":"en/ez/d-/20/en-ezd-200.html","edd-149":"en/ed/d-/14/en-edd-149.html","ezd-201":"en/ez/d-/20/en-ezd-201.html","esb-018":"en/es/b-/01/en-esb-018.html","esb-017":"en/es/b-/01/en-esb-017.html","edd-148":"en/ed/d-/14/en-edd-148.html","erdl-003":"en/er/dl/-0/en-erdl-003.html","edgd-162":"en/ed/gd/-1/en-edgd-162.html","emaf-001":"en/em/af/-0/en-emaf-001.html","emaz-003":"en/em/az/-0/en-emaz-003.html","emaz-002":"en/em/az/-0/en-emaz-002.html","emad-001":"en/em/ad/-0/en-emad-001.html","emaz-001":"en/em/az/-0/en-emaz-001.html","etc-006":"en/et/c-/00/en-etc-006.html","evo-069":"en/ev/o-/06/en-evo-069.html","evo-070":"en/ev/o-/07/en-evo-070.html","ezd-199":"en/ez/d-/19/en-ezd-199.html","ezd-198":"en/ez/d-/19/en-ezd-198.html","ezd-197":"en/ez/d-/19/en-ezd-197.html","ekdv-028":"en/ek/dv/-0/en-ekdv-028.html","ekdv-027":"en/ek/dv/-0/en-ekdv-027.html","elo-200":"en/el/o-/20/en-elo-200.html","elo-202":"en/el/o-/20/en-elo-202.html","elo-205":"en/el/o-/20/en-elo-205.html","elo-203":"en/el/o-/20/en-elo-203.html","ezd-193":"en/ez/d-/19/en-ezd-193.html","ezd-194":"en/ez/d-/19/en-ezd-194.html","emu-031":"en/em/u-/03/en-emu-031.html","ezd-191":"en/ez/d-/19/en-ezd-191.html","ezd-195":"en/ez/d-/19/en-ezd-195.html","ezd-196":"en/ez/d-/19/en-ezd-196.html","ebod-062":"en/eb/od/-0/en-ebod-062.html","ebod-064":"en/eb/od/-0/en-ebod-064.html","ebod-063":"en/eb/od/-0/en-ebod-063.html","emu-027":"en/em/u-/02/en-emu-027.html","ekdv-026":"en/ek/dv/-0/en-ekdv-026.html","ekdv-025":"en/ek/dv/-0/en-ekdv-025.html","ecb-033":"en/ec/b-/03/en-ecb-033.html","edd-147":"en/ed/d-/14/en-edd-147.html","edd-146":"en/ed/d-/14/en-edd-146.html","eok-006":"en/eo/k-/00/en-eok-006.html","esb-015":"en/es/b-/01/en-esb-015.html","esb-016":"en/es/b-/01/en-esb-016.html","edgd-161":"en/ed/gd/-1/en-edgd-161.html","edgd-160":"en/ed/gd/-1/en-edgd-160.html","ezd-190":"en/ez/d-/19/en-ezd-190.html","ecb-002":"en/ec/b-/00/en-ecb-002.html","ekdv-024":"en/ek/dv/-0/en-ekdv-024.html","evo-065":"en/ev/o-/06/en-evo-065.html","ekdv-023":"en/ek/dv/-0/en-ekdv-023.html","elo-195":"en/el/o-/19/en-elo-195.html","ezd-189":"en/ez/d-/18/en-ezd-189.html","elo-196":"en/el/o-/19/en-elo-196.html","elo-199":"en/el/o-/19/en-elo-199.html","elo-198":"en/el/o-/19/en-elo-198.html","evo-066":"en/ev/o-/06/en-evo-066.html","ekdv-022":"en/ek/dv/-0/en-ekdv-022.html","ebod-058":"en/eb/od/-0/en-ebod-058.html","ebod-061":"en/eb/od/-0/en-ebod-061.html","ebod-060":"en/eb/od/-0/en-ebod-060.html","ebod-059":"en/eb/od/-0/en-ebod-059.html","eud-001":"en/eu/d-/00/en-eud-001.html","eud-002":"en/eu/d-/00/en-eud-002.html","ec-058":"en/ec/-0/58/en-ec-058.html","ezd-188":"en/ez/d-/18/en-ezd-188.html","ezd-187":"en/ez/d-/18/en-ezd-187.html","ezd-186":"en/ez/d-/18/en-ezd-186.html","erod-089":"en/er/od/-0/en-erod-089.html","ecb-032":"en/ec/b-/03/en-ecb-032.html","esb-013":"en/es/b-/01/en-esb-013.html","edd-144":"en/ed/d-/14/en-edd-144.html","edd-145":"en/ed/d-/14/en-edd-145.html","ezd-183":"en/ez/d-/18/en-ezd-183.html","edgd-159":"en/ed/gd/-1/en-edgd-159.html","edgd-158":"en/ed/gd/-1/en-edgd-158.html","evo-062":"en/ev/o-/06/en-evo-062.html","evo-061":"en/ev/o-/06/en-evo-061.html","ezd-182":"en/ez/d-/18/en-ezd-182.html","ec-056":"en/ec/-0/56/en-ec-056.html","elo-190":"en/el/o-/19/en-elo-190.html","elo-193":"en/el/o-/19/en-elo-193.html","elo-191":"en/el/o-/19/en-elo-191.html","elo-189":"en/el/o-/18/en-elo-189.html","ekdv-021":"en/ek/dv/-0/en-ekdv-021.html","ecb-031":"en/ec/b-/03/en-ecb-031.html","ebod-054":"en/eb/od/-0/en-ebod-054.html","ebod-056":"en/eb/od/-0/en-ebod-056.html","ebod-055":"en/eb/od/-0/en-ebod-055.html","ebod-057":"en/eb/od/-0/en-ebod-057.html","ezd-180":"en/ez/d-/18/en-ezd-180.html","ekdv-020":"en/ek/dv/-0/en-ekdv-020.html","ebl-001":"en/eb/l-/00/en-ebl-001.html","edgd-157":"en/ed/gd/-1/en-edgd-157.html","edgd-156":"en/ed/gd/-1/en-edgd-156.html","esb-012":"en/es/b-/01/en-esb-012.html","ezd-176":"en/ez/d-/17/en-ezd-176.html","edd-142":"en/ed/d-/14/en-edd-142.html","esb-011":"en/es/b-/01/en-esb-011.html","ec-053":"en/ec/-0/53/en-ec-053.html","emu-025":"en/em/u-/02/en-emu-025.html","ec-054":"en/ec/-0/54/en-ec-054.html","ec-055":"en/ec/-0/55/en-ec-055.html","emu-026":"en/em/u-/02/en-emu-026.html","evo-058":"en/ev/o-/05/en-evo-058.html","evo-057":"en/ev/o-/05/en-evo-057.html","egg-013":"en/eg/g-/01/en-egg-013.html","egg-014":"en/eg/g-/01/en-egg-014.html","elo-184":"en/el/o-/18/en-elo-184.html","elo-188":"en/el/o-/18/en-elo-188.html","elo-186":"en/el/o-/18/en-elo-186.html","ebod-050":"en/eb/od/-0/en-ebod-050.html","ebod-052":"en/eb/od/-0/en-ebod-052.html","ebod-053":"en/eb/od/-0/en-ebod-053.html","ebod-051":"en/eb/od/-0/en-ebod-051.html","ezd-171":"en/ez/d-/17/en-ezd-171.html","ezd-174":"en/ez/d-/17/en-ezd-174.html","ezd-172":"en/ez/d-/17/en-ezd-172.html","ezd-175":"en/ez/d-/17/en-ezd-175.html","ecb-030":"en/ec/b-/03/en-ecb-030.html","ekdv-017":"en/ek/dv/-0/en-ekdv-017.html","edd-140":"en/ed/d-/14/en-edd-140.html","edd-141":"en/ed/d-/14/en-edd-141.html","esb-009":"en/es/b-/00/en-esb-009.html","esb-010":"en/es/b-/01/en-esb-010.html","edgd-155":"en/ed/gd/-1/en-edgd-155.html","edgd-154":"en/ed/gd/-1/en-edgd-154.html","ezd-168":"en/ez/d-/16/en-ezd-168.html","evo-053":"en/ev/o-/05/en-evo-053.html","evo-054":"en/ev/o-/05/en-evo-054.html","ezd-167":"en/ez/d-/16/en-ezd-167.html","ezd-166":"en/ez/d-/16/en-ezd-166.html","elo-181":"en/el/o-/18/en-elo-181.html","elo-183":"en/el/o-/18/en-elo-183.html","elo-182":"en/el/o-/18/en-elo-182.html","elo-179":"en/el/o-/17/en-elo-179.html","elo-178":"en/el/o-/17/en-elo-178.html","ezd-163":"en/ez/d-/16/en-ezd-163.html","ezd-162":"en/ez/d-/16/en-ezd-162.html","ezd-160":"en/ez/d-/16/en-ezd-160.html","ezd-165":"en/ez/d-/16/en-ezd-165.html","ezd-161":"en/ez/d-/16/en-ezd-161.html","ebod-047":"en/eb/od/-0/en-ebod-047.html","ebod-046":"en/eb/od/-0/en-ebod-046.html","ebod-049":"en/eb/od/-0/en-ebod-049.html","ekdv-015":"en/ek/dv/-0/en-ekdv-015.html","emu-021":"en/em/u-/02/en-emu-021.html","ekdv-016":"en/ek/dv/-0/en-ekdv-016.html","ecb-029":"en/ec/b-/02/en-ecb-029.html","edd-139":"en/ed/d-/13/en-edd-139.html","edd-138":"en/ed/d-/13/en-edd-138.html","esb-007":"en/es/b-/00/en-esb-007.html","esb-008":"en/es/b-/00/en-esb-008.html","ezd-159":"en/ez/d-/15/en-ezd-159.html","edgd-153":"en/ed/gd/-1/en-edgd-153.html","edgd-152":"en/ed/gd/-1/en-edgd-152.html","eok-005":"en/eo/k-/00/en-eok-005.html","evo-050":"en/ev/o-/05/en-evo-050.html","evo-049":"en/ev/o-/04/en-evo-049.html","ezd-158":"en/ez/d-/15/en-ezd-158.html","elo-177":"en/el/o-/17/en-elo-177.html","elo-175":"en/el/o-/17/en-elo-175.html","elo-176":"en/el/o-/17/en-elo-176.html","elo-173":"en/el/o-/17/en-elo-173.html","elo-174":"en/el/o-/17/en-elo-174.html","ekdv-013":"en/ek/dv/-0/en-ekdv-013.html","eok-004":"en/eo/k-/00/en-eok-004.html","ezd-155":"en/ez/d-/15/en-ezd-155.html","ebod-039":"en/eb/od/-0/en-ebod-039.html","ebod-038":"en/eb/od/-0/en-ebod-038.html","ebod-041":"en/eb/od/-0/en-ebod-041.html","ebod-042":"en/eb/od/-0/en-ebod-042.html","ebod-044":"en/eb/od/-0/en-ebod-044.html","ebod-040":"en/eb/od/-0/en-ebod-040.html","ezd-154":"en/ez/d-/15/en-ezd-154.html","ebod-045":"en/eb/od/-0/en-ebod-045.html","ebod-043":"en/eb/od/-0/en-ebod-043.html","ezd-156":"en/ez/d-/15/en-ezd-156.html","ezd-157":"en/ez/d-/15/en-ezd-157.html","ezd-153":"en/ez/d-/15/en-ezd-153.html","ec-043":"en/ec/-0/43/en-ec-043.html","erod-082":"en/er/od/-0/en-erod-082.html","erod-073":"en/er/od/-0/en-erod-073.html","erod-072":"en/er/od/-0/en-erod-072.html","ecb-028":"en/ec/b-/02/en-ecb-028.html","edgd-151":"en/ed/gd/-1/en-edgd-151.html","edgd-150":"en/ed/gd/-1/en-edgd-150.html","ezd-152":"en/ez/d-/15/en-ezd-152.html","ezd-151":"en/ez/d-/15/en-ezd-151.html","esb-005":"en/es/b-/00/en-esb-005.html","esb-006":"en/es/b-/00/en-esb-006.html","edd-137":"en/ed/d-/13/en-edd-137.html","edd-136":"en/ed/d-/13/en-edd-136.html","evo-046":"en/ev/o-/04/en-evo-046.html","evo-044":"en/ev/o-/04/en-evo-044.html","evo-045":"en/ev/o-/04/en-evo-045.html","ezd-149":"en/ez/d-/14/en-ezd-149.html","ezd-150":"en/ez/d-/15/en-ezd-150.html","ezd-148":"en/ez/d-/14/en-ezd-148.html","elo-170":"en/el/o-/17/en-elo-170.html","elo-172":"en/el/o-/17/en-elo-172.html","elo-169":"en/el/o-/16/en-elo-169.html","elo-168":"en/el/o-/16/en-elo-168.html","ekdv-012":"en/ek/dv/-0/en-ekdv-012.html","ebod-033":"en/eb/od/-0/en-ebod-033.html","ebod-037":"en/eb/od/-0/en-ebod-037.html","ebod-034":"en/eb/od/-0/en-ebod-034.html","ebod-035":"en/eb/od/-0/en-ebod-035.html","ebod-036":"en/eb/od/-0/en-ebod-036.html","ezd-144":"en/ez/d-/14/en-ezd-144.html","ezd-145":"en/ez/d-/14/en-ezd-145.html","ezd-147":"en/ez/d-/14/en-ezd-147.html","ezd-146":"en/ez/d-/14/en-ezd-146.html","edd-135":"en/ed/d-/13/en-edd-135.html","esb-003":"en/es/b-/00/en-esb-003.html","edd-134":"en/ed/d-/13/en-edd-134.html","ezd-143":"en/ez/d-/14/en-ezd-143.html","ezd-142":"en/ez/d-/14/en-ezd-142.html","esb-004":"en/es/b-/00/en-esb-004.html","edgd-149":"en/ed/gd/-1/en-edgd-149.html","eok-003":"en/eo/k-/00/en-eok-003.html","emu-013":"en/em/u-/01/en-emu-013.html","evo-041":"en/ev/o-/04/en-evo-041.html","ezd-141":"en/ez/d-/14/en-ezd-141.html","egg-011":"en/eg/g-/01/en-egg-011.html","egg-012":"en/eg/g-/01/en-egg-012.html","ekdv-010":"en/ek/dv/-0/en-ekdv-010.html","elo-165":"en/el/o-/16/en-elo-165.html","elo-164":"en/el/o-/16/en-elo-164.html","elo-167":"en/el/o-/16/en-elo-167.html","emu-014":"en/em/u-/01/en-emu-014.html","emp-008":"en/em/p-/00/en-emp-008.html","ezd-135":"en/ez/d-/13/en-ezd-135.html","ezd-136":"en/ez/d-/13/en-ezd-136.html","ezd-139":"en/ez/d-/13/en-ezd-139.html","ebod-030":"en/eb/od/-0/en-ebod-030.html","ebod-032":"en/eb/od/-0/en-ebod-032.html","ebod-029":"en/eb/od/-0/en-ebod-029.html","ebod-031":"en/eb/od/-0/en-ebod-031.html","ecb-026":"en/ec/b-/02/en-ecb-026.html","edd-132":"en/ed/d-/13/en-edd-132.html","esb-002":"en/es/b-/00/en-esb-002.html","esb-001":"en/es/b-/00/en-esb-001.html","edd-133":"en/ed/d-/13/en-edd-133.html","ezd-134":"en/ez/d-/13/en-ezd-134.html","edgd-148":"en/ed/gd/-1/en-edgd-148.html","edgd-147":"en/ed/gd/-1/en-edgd-147.html","ekdv-009":"en/ek/dv/-0/en-ekdv-009.html","evo-037":"en/ev/o-/03/en-evo-037.html","egg-009":"en/eg/g-/00/en-egg-009.html","elo-161":"en/el/o-/16/en-elo-161.html","elo-159":"en/el/o-/15/en-elo-159.html","elo-163":"en/el/o-/16/en-elo-163.html","ebod-024":"en/eb/od/-0/en-ebod-024.html","ebod-026":"en/eb/od/-0/en-ebod-026.html","ebod-025":"en/eb/od/-0/en-ebod-025.html","ekdv-008":"en/ek/dv/-0/en-ekdv-008.html","ebod-028":"en/eb/od/-0/en-ebod-028.html","ebod-027":"en/eb/od/-0/en-ebod-027.html","ezd-132":"en/ez/d-/13/en-ezd-132.html","ezd-131":"en/ez/d-/13/en-ezd-131.html","ewd-002":"en/ew/d-/00/en-ewd-002.html","ecb-025":"en/ec/b-/02/en-ecb-025.html","edd-131":"en/ed/d-/13/en-edd-131.html","ezd-130":"en/ez/d-/13/en-ezd-130.html","edd-130":"en/ed/d-/13/en-edd-130.html","edgd-145":"en/ed/gd/-1/en-edgd-145.html","eok-002":"en/eo/k-/00/en-eok-002.html","ezd-128":"en/ez/d-/12/en-ezd-128.html","ezd-129":"en/ez/d-/12/en-ezd-129.html","evo-032":"en/ev/o-/03/en-evo-032.html","evo-033":"en/ev/o-/03/en-evo-033.html","elo-155":"en/el/o-/15/en-elo-155.html","elo-154":"en/el/o-/15/en-elo-154.html","elo-153":"en/el/o-/15/en-elo-153.html","elo-156":"en/el/o-/15/en-elo-156.html","elo-157":"en/el/o-/15/en-elo-157.html","erod-092":"en/er/od/-0/en-erod-092.html","erod-077":"en/er/od/-0/en-erod-077.html","erod-078":"en/er/od/-0/en-erod-078.html","erod-091":"en/er/od/-0/en-erod-091.html","eld-003":"en/el/d-/00/en-eld-003.html","ebod-021":"en/eb/od/-0/en-ebod-021.html","ebod-022":"en/eb/od/-0/en-ebod-022.html","ebod-023":"en/eb/od/-0/en-ebod-023.html","ezd-124":"en/ez/d-/12/en-ezd-124.html","ezd-126":"en/ez/d-/12/en-ezd-126.html","ezd-127":"en/ez/d-/12/en-ezd-127.html","ekdv-006":"en/ek/dv/-0/en-ekdv-006.html","ecb-024":"en/ec/b-/02/en-ecb-024.html","edd-129":"en/ed/d-/12/en-edd-129.html","edd-128":"en/ed/d-/12/en-edd-128.html","ezd-122":"en/ez/d-/12/en-ezd-122.html","eok-001":"en/eo/k-/00/en-eok-001.html","edgd-144":"en/ed/gd/-1/en-edgd-144.html","edgd-143":"en/ed/gd/-1/en-edgd-143.html","ekdv-005":"en/ek/dv/-0/en-ekdv-005.html","ec-037":"en/ec/-0/37/en-ec-037.html","evo-029":"en/ev/o-/02/en-evo-029.html","evo-028":"en/ev/o-/02/en-evo-028.html","egg-007":"en/eg/g-/00/en-egg-007.html","egg-008":"en/eg/g-/00/en-egg-008.html","elo-150":"en/el/o-/15/en-elo-150.html","elo-146":"en/el/o-/14/en-elo-146.html","elo-148":"en/el/o-/14/en-elo-148.html","elo-147":"en/el/o-/14/en-elo-147.html","elo-149":"en/el/o-/14/en-elo-149.html","ekdv-004":"en/ek/dv/-0/en-ekdv-004.html","ezd-117":"en/ez/d-/11/en-ezd-117.html","ezd-118":"en/ez/d-/11/en-ezd-118.html","ezd-119":"en/ez/d-/11/en-ezd-119.html","ezd-120":"en/ez/d-/12/en-ezd-120.html","ebod-018":"en/eb/od/-0/en-ebod-018.html","ebod-019":"en/eb/od/-0/en-ebod-019.html","ebod-020":"en/eb/od/-0/en-ebod-020.html","ebod-017":"en/eb/od/-0/en-ebod-017.html","ewd-001":"en/ew/d-/00/en-ewd-001.html","edd-127":"en/ed/d-/12/en-edd-127.html","edd-126":"en/ed/d-/12/en-edd-126.html","edgd-140":"en/ed/gd/-1/en-edgd-140.html","edgd-141":"en/ed/gd/-1/en-edgd-141.html","edgd-142":"en/ed/gd/-1/en-edgd-142.html","edgd-139":"en/ed/gd/-1/en-edgd-139.html","emu-008":"en/em/u-/00/en-emu-008.html","ekdv-002":"en/ek/dv/-0/en-ekdv-002.html","emu-006":"en/em/u-/00/en-emu-006.html","ekdv-003":"en/ek/dv/-0/en-ekdv-003.html","evo-024":"en/ev/o-/02/en-evo-024.html","evo-023":"en/ev/o-/02/en-evo-023.html","evo-025":"en/ev/o-/02/en-evo-025.html","egg-005":"en/eg/g-/00/en-egg-005.html","egg-006":"en/eg/g-/00/en-egg-006.html","elo-143":"en/el/o-/14/en-elo-143.html","elo-142":"en/el/o-/14/en-elo-142.html","elo-144":"en/el/o-/14/en-elo-144.html","elo-145":"en/el/o-/14/en-elo-145.html","ebod-015":"en/eb/od/-0/en-ebod-015.html","ebod-013":"en/eb/od/-0/en-ebod-013.html","ezd-115":"en/ez/d-/11/en-ezd-115.html","ezd-114":"en/ez/d-/11/en-ezd-114.html","ebod-014":"en/eb/od/-0/en-ebod-014.html","ebod-016":"en/eb/od/-0/en-ebod-016.html","ezd-112":"en/ez/d-/11/en-ezd-112.html","ezd-113":"en/ez/d-/11/en-ezd-113.html","ecb-022":"en/ec/b-/02/en-ecb-022.html","ezd-111":"en/ez/d-/11/en-ezd-111.html","edd-124":"en/ed/d-/12/en-edd-124.html","edd-125":"en/ed/d-/12/en-edd-125.html","edgd-138":"en/ed/gd/-1/en-edgd-138.html","edgd-136":"en/ed/gd/-1/en-edgd-136.html","edgd-135":"en/ed/gd/-1/en-edgd-135.html","edgd-137":"en/ed/gd/-1/en-edgd-137.html","egg-004":"en/eg/g-/00/en-egg-004.html","egg-003":"en/eg/g-/00/en-egg-003.html","evo-019":"en/ev/o-/01/en-evo-019.html","eye-009":"en/ey/e-/00/en-eye-009.html","elo-140":"en/el/o-/14/en-elo-140.html","elo-138":"en/el/o-/13/en-elo-138.html","elo-139":"en/el/o-/13/en-elo-139.html","ebod-010":"en/eb/od/-0/en-ebod-010.html","ebod-011":"en/eb/od/-0/en-ebod-011.html","ebod-009":"en/eb/od/-0/en-ebod-009.html","ebod-012":"en/eb/od/-0/en-ebod-012.html","ezd-107":"en/ez/d-/10/en-ezd-107.html","ezd-108":"en/ez/d-/10/en-ezd-108.html","ezd-109":"en/ez/d-/10/en-ezd-109.html","ezd-110":"en/ez/d-/11/en-ezd-110.html","ecb-021":"en/ec/b-/02/en-ecb-021.html","edgd-131":"en/ed/gd/-1/en-edgd-131.html","ezd-105":"en/ez/d-/10/en-ezd-105.html","edgd-132":"en/ed/gd/-1/en-edgd-132.html","edd-123":"en/ed/d-/12/en-edd-123.html","edd-122":"en/ed/d-/12/en-edd-122.html","edgd-134":"en/ed/gd/-1/en-edgd-134.html","edgd-133":"en/ed/gd/-1/en-edgd-133.html","elo-135":"en/el/o-/13/en-elo-135.html","elo-134":"en/el/o-/13/en-elo-134.html","elo-132":"en/el/o-/13/en-elo-132.html","elo-137":"en/el/o-/13/en-elo-137.html","ec-024":"en/ec/-0/24/en-ec-024.html","evo-015":"en/ev/o-/01/en-evo-015.html","evo-016":"en/ev/o-/01/en-evo-016.html","egg-002":"en/eg/g-/00/en-egg-002.html","ezd-104":"en/ez/d-/10/en-ezd-104.html","ebod-006":"en/eb/od/-0/en-ebod-006.html","ebod-007":"en/eb/od/-0/en-ebod-007.html","ezd-102":"en/ez/d-/10/en-ezd-102.html","ebod-008":"en/eb/od/-0/en-ebod-008.html","ezd-101":"en/ez/d-/10/en-ezd-101.html","ezd-103":"en/ez/d-/10/en-ezd-103.html","edd-121":"en/ed/d-/12/en-edd-121.html","ecb-020":"en/ec/b-/02/en-ecb-020.html","edgd-128":"en/ed/gd/-1/en-edgd-128.html","edgd-127":"en/ed/gd/-1/en-edgd-127.html","edd-120":"en/ed/d-/12/en-edd-120.html","edgd-130":"en/ed/gd/-1/en-edgd-130.html","edgd-129":"en/ed/gd/-1/en-edgd-129.html","elo-127":"en/el/o-/12/en-elo-127.html","elo-128":"en/el/o-/12/en-elo-128.html","elo-130":"en/el/o-/13/en-elo-130.html","elo-131":"en/el/o-/13/en-elo-131.html","evo-011":"en/ev/o-/01/en-evo-011.html","egg-001":"en/eg/g-/00/en-egg-001.html","evo-012":"en/ev/o-/01/en-evo-012.html","ebod-001":"en/eb/od/-0/en-ebod-001.html","ebod-004":"en/eb/od/-0/en-ebod-004.html","ebod-003":"en/eb/od/-0/en-ebod-003.html","ebod-002":"en/eb/od/-0/en-ebod-002.html","ezd-096":"en/ez/d-/09/en-ezd-096.html","ezd-098":"en/ez/d-/09/en-ezd-098.html","ezd-097":"en/ez/d-/09/en-ezd-097.html","ec-017":"en/ec/-0/17/en-ec-017.html","ecb-019":"en/ec/b-/01/en-ecb-019.html","eld-001":"en/el/d-/00/en-eld-001.html","edd-118":"en/ed/d-/11/en-edd-118.html","edd-119":"en/ed/d-/11/en-edd-119.html","edgd-125":"en/ed/gd/-1/en-edgd-125.html","edgd-126":"en/ed/gd/-1/en-edgd-126.html","elo-124":"en/el/o-/12/en-elo-124.html","elo-121":"en/el/o-/12/en-elo-121.html","elo-125":"en/el/o-/12/en-elo-125.html","elo-122":"en/el/o-/12/en-elo-122.html","elo-123":"en/el/o-/12/en-elo-123.html","elo-126":"en/el/o-/12/en-elo-126.html","evo-009":"en/ev/o-/00/en-evo-009.html","ezd-091":"en/ez/d-/09/en-ezd-091.html","ezd-092":"en/ez/d-/09/en-ezd-092.html","ezd-093":"en/ez/d-/09/en-ezd-093.html","ecb-018":"en/ec/b-/01/en-ecb-018.html","edd-117":"en/ed/d-/11/en-edd-117.html","edd-116":"en/ed/d-/11/en-edd-116.html","edgd-121":"en/ed/gd/-1/en-edgd-121.html","edgd-122":"en/ed/gd/-1/en-edgd-122.html","edgd-123":"en/ed/gd/-1/en-edgd-123.html","edgd-124":"en/ed/gd/-1/en-edgd-124.html","elo-118":"en/el/o-/11/en-elo-118.html","elo-116":"en/el/o-/11/en-elo-116.html","elo-119":"en/el/o-/11/en-elo-119.html","elo-117":"en/el/o-/11/en-elo-117.html","elo-120":"en/el/o-/12/en-elo-120.html","ezd-086":"en/ez/d-/08/en-ezd-086.html","ezd-087":"en/ez/d-/08/en-ezd-087.html","ezd-088":"en/ez/d-/08/en-ezd-088.html","ecb-017":"en/ec/b-/01/en-ecb-017.html","edgd-117":"en/ed/gd/-1/en-edgd-117.html","edd-114":"en/ed/d-/11/en-edd-114.html","edgd-119":"en/ed/gd/-1/en-edgd-119.html","edgd-120":"en/ed/gd/-1/en-edgd-120.html","edd-115":"en/ed/d-/11/en-edd-115.html","ezfx-001":"en/ez/fx/-0/en-ezfx-001.html","euil-001":"en/eu/il/-0/en-euil-001.html","elo-113":"en/el/o-/11/en-elo-113.html","elo-109":"en/el/o-/10/en-elo-109.html","elo-111":"en/el/o-/11/en-elo-111.html","elo-112":"en/el/o-/11/en-elo-112.html","elo-114":"en/el/o-/11/en-elo-114.html","elo-115":"en/el/o-/11/en-elo-115.html","evo-006":"en/ev/o-/00/en-evo-006.html","ephl-001":"en/ep/hl/-0/en-ephl-001.html","eqgx-001":"en/eq/gx/-0/en-eqgx-001.html","exkl-001":"en/ex/kl/-0/en-exkl-001.html","evo-005":"en/ev/o-/00/en-evo-005.html","ezd-082":"en/ez/d-/08/en-ezd-082.html","ezd-083":"en/ez/d-/08/en-ezd-083.html","egxx-001":"en/eg/xx/-0/en-egxx-001.html","ecb-016":"en/ec/b-/01/en-ecb-016.html","ejal-001":"en/ej/al/-0/en-ejal-001.html","edgd-114":"en/ed/gd/-1/en-edgd-114.html","edgd-113":"en/ed/gd/-1/en-edgd-113.html","edd-113":"en/ed/d-/11/en-edd-113.html","ezxx-001":"en/ez/xx/-0/en-ezxx-001.html","elo-107":"en/el/o-/10/en-elo-107.html","elo-110":"en/el/o-/11/en-elo-110.html","elo-106":"en/el/o-/10/en-elo-106.html","ezd-080":"en/ez/d-/08/en-ezd-080.html","ezd-079":"en/ez/d-/07/en-ezd-079.html","ezd-077":"en/ez/d-/07/en-ezd-077.html","ezd-078":"en/ez/d-/07/en-ezd-078.html","evo-003":"en/ev/o-/00/en-evo-003.html","ecb-015":"en/ec/b-/01/en-ecb-015.html","edd-110":"en/ed/d-/11/en-edd-110.html","edd-111":"en/ed/d-/11/en-edd-111.html","edgd-112":"en/ed/gd/-1/en-edgd-112.html","edgd-109":"en/ed/gd/-1/en-edgd-109.html","edgd-110":"en/ed/gd/-1/en-edgd-110.html","erwl-001":"en/er/wl/-0/en-erwl-001.html","elo-102":"en/el/o-/10/en-elo-102.html","elo-101":"en/el/o-/10/en-elo-101.html","elo-105":"en/el/o-/10/en-elo-105.html","elo-104":"en/el/o-/10/en-elo-104.html","ecel-001":"en/ec/el/-0/en-ecel-001.html","ezd-070":"en/ez/d-/07/en-ezd-070.html","ekhl-001":"en/ek/hl/-0/en-ekhl-001.html","ezd-074":"en/ez/d-/07/en-ezd-074.html","ezd-075":"en/ez/d-/07/en-ezd-075.html","ecb-007":"en/ec/b-/00/en-ecb-007.html","ebtx-001":"en/eb/tx/-0/en-ebtx-001.html","ecb-014":"en/ec/b-/01/en-ecb-014.html","ewgx-001":"en/ew/gx/-0/en-ewgx-001.html","ecb-006":"en/ec/b-/00/en-ecb-006.html","edgd-108":"en/ed/gd/-1/en-edgd-108.html","edgd-105":"en/ed/gd/-1/en-edgd-105.html","edd-108":"en/ed/d-/10/en-edd-108.html","edd-109":"en/ed/d-/10/en-edd-109.html","ecb-001":"en/ec/b-/00/en-ecb-001.html","elo-098":"en/el/o-/09/en-elo-098.html","elo-099":"en/el/o-/09/en-elo-099.html","elo-100":"en/el/o-/10/en-elo-100.html","ezd-071":"en/ez/d-/07/en-ezd-071.html","ecb-004":"en/ec/b-/00/en-ecb-004.html","eddx-001":"en/ed/dx/-0/en-eddx-001.html","ecb-013":"en/ec/b-/01/en-ecb-013.html","edd-106":"en/ed/d-/10/en-edd-106.html","edd-107":"en/ed/d-/10/en-edd-107.html","edgd-104":"en/ed/gd/-1/en-edgd-104.html","edgd-103":"en/ed/gd/-1/en-edgd-103.html","elo-094":"en/el/o-/09/en-elo-094.html","elo-097":"en/el/o-/09/en-elo-097.html","elo-095":"en/el/o-/09/en-elo-095.html","elo-096":"en/el/o-/09/en-elo-096.html","eye-006":"en/ey/e-/00/en-eye-006.html","ecb-012":"en/ec/b-/01/en-ecb-012.html","ecb-011":"en/ec/b-/01/en-ecb-011.html","ecb-005":"en/ec/b-/00/en-ecb-005.html","edd-105":"en/ed/d-/10/en-edd-105.html","edd-104":"en/ed/d-/10/en-edd-104.html","elo-092":"en/el/o-/09/en-elo-092.html","elo-091":"en/el/o-/09/en-elo-091.html","elo-093":"en/el/o-/09/en-elo-093.html","ezd-065":"en/ez/d-/06/en-ezd-065.html","ezd-064":"en/ez/d-/06/en-ezd-064.html","ecb-010":"en/ec/b-/01/en-ecb-010.html","exd-057":"en/ex/d-/05/en-exd-057.html","ecb-003":"en/ec/b-/00/en-ecb-003.html","edd-103":"en/ed/d-/10/en-edd-103.html","edd-102":"en/ed/d-/10/en-edd-102.html","edgd-100":"en/ed/gd/-1/en-edgd-100.html","edgd-099":"en/ed/gd/-0/en-edgd-099.html","elo-088":"en/el/o-/08/en-elo-088.html","elo-087":"en/el/o-/08/en-elo-087.html","elo-089":"en/el/o-/08/en-elo-089.html","elo-090":"en/el/o-/09/en-elo-090.html","ezd-059":"en/ez/d-/05/en-ezd-059.html","ezd-063":"en/ez/d-/06/en-ezd-063.html","ezd-057":"en/ez/d-/05/en-ezd-057.html","eafx-001":"en/ea/fx/-0/en-eafx-001.html","ecb-009":"en/ec/b-/00/en-ecb-009.html","ecb-008":"en/ec/b-/00/en-ecb-008.html","edd-101":"en/ed/d-/10/en-edd-101.html","edd-100":"en/ed/d-/10/en-edd-100.html","edgd-096":"en/ed/gd/-0/en-edgd-096.html","edgd-097":"en/ed/gd/-0/en-edgd-097.html","edgd-098":"en/ed/gd/-0/en-edgd-098.html","elo-086":"en/el/o-/08/en-elo-086.html","elo-085":"en/el/o-/08/en-elo-085.html","eczl-001":"en/ec/zl/-0/en-eczl-001.html","edd-099":"en/ed/d-/09/en-edd-099.html","edd-098":"en/ed/d-/09/en-edd-098.html","eye-005":"en/ey/e-/00/en-eye-005.html","eye-004":"en/ey/e-/00/en-eye-004.html","erml-001":"en/er/ml/-0/en-erml-001.html","edgd-093":"en/ed/gd/-0/en-edgd-093.html","edgd-094":"en/ed/gd/-0/en-edgd-094.html","edgd-095":"en/ed/gd/-0/en-edgd-095.html","elo-078":"en/el/o-/07/en-elo-078.html","elo-077":"en/el/o-/07/en-elo-077.html","elo-076":"en/el/o-/07/en-elo-076.html","elo-079":"en/el/o-/07/en-elo-079.html","elo-081":"en/el/o-/08/en-elo-081.html","elo-080":"en/el/o-/08/en-elo-080.html","elo-084":"en/el/o-/08/en-elo-084.html","elo-082":"en/el/o-/08/en-elo-082.html","elo-083":"en/el/o-/08/en-elo-083.html","efxl-001":"en/ef/xl/-0/en-efxl-001.html","ezd-053":"en/ez/d-/05/en-ezd-053.html","ezd-052":"en/ez/d-/05/en-ezd-052.html","eye-003":"en/ey/e-/00/en-eye-003.html","ezd-051":"en/ez/d-/05/en-ezd-051.html","edd-097":"en/ed/d-/09/en-edd-097.html","edd-096":"en/ed/d-/09/en-edd-096.html","eoll-001":"en/eo/ll/-0/en-eoll-001.html","edgd-090":"en/ed/gd/-0/en-edgd-090.html","edgd-092":"en/ed/gd/-0/en-edgd-092.html","edgd-091":"en/ed/gd/-0/en-edgd-091.html","elo-072":"en/el/o-/07/en-elo-072.html","elo-071":"en/el/o-/07/en-elo-071.html","elo-070":"en/el/o-/07/en-elo-070.html","elo-075":"en/el/o-/07/en-elo-075.html","elo-074":"en/el/o-/07/en-elo-074.html","elo-073":"en/el/o-/07/en-elo-073.html","ezd-048":"en/ez/d-/04/en-ezd-048.html","edd-087":"en/ed/d-/08/en-edd-087.html","ezd-018":"en/ez/d-/01/en-ezd-018.html","ezd-045":"en/ez/d-/04/en-ezd-045.html","ezd-047":"en/ez/d-/04/en-ezd-047.html","eye-002":"en/ey/e-/00/en-eye-002.html","ezd-044":"en/ez/d-/04/en-ezd-044.html","ezd-046":"en/ez/d-/04/en-ezd-046.html","edd-094":"en/ed/d-/09/en-edd-094.html","edd-095":"en/ed/d-/09/en-edd-095.html","edgd-087":"en/ed/gd/-0/en-edgd-087.html","edgd-088":"en/ed/gd/-0/en-edgd-088.html","elo-069":"en/el/o-/06/en-elo-069.html","elo-066":"en/el/o-/06/en-elo-066.html","elo-064":"en/el/o-/06/en-elo-064.html","elo-065":"en/el/o-/06/en-elo-065.html","elo-068":"en/el/o-/06/en-elo-068.html","elo-067":"en/el/o-/06/en-elo-067.html","etpx-002":"en/et/px/-0/en-etpx-002.html","ezd-041":"en/ez/d-/04/en-ezd-041.html","ezd-037":"en/ez/d-/03/en-ezd-037.html","ezd-040":"en/ez/d-/04/en-ezd-040.html","ezd-035":"en/ez/d-/03/en-ezd-035.html","ezd-036":"en/ez/d-/03/en-ezd-036.html","ezd-042":"en/ez/d-/04/en-ezd-042.html","ehgl-001":"en/eh/gl/-0/en-ehgl-001.html","etpx-001":"en/et/px/-0/en-etpx-001.html","edd-093":"en/ed/d-/09/en-edd-093.html","edd-090":"en/ed/d-/09/en-edd-090.html","edd-092":"en/ed/d-/09/en-edd-092.html","edd-091":"en/ed/d-/09/en-edd-091.html","edgd-085":"en/ed/gd/-0/en-edgd-085.html","elo-060":"en/el/o-/06/en-elo-060.html","elo-059":"en/el/o-/05/en-elo-059.html","elo-058":"en/el/o-/05/en-elo-058.html","elo-057":"en/el/o-/05/en-elo-057.html","elo-055":"en/el/o-/05/en-elo-055.html","elo-056":"en/el/o-/05/en-elo-056.html","elo-063":"en/el/o-/06/en-elo-063.html","elo-062":"en/el/o-/06/en-elo-062.html","elo-061":"en/el/o-/06/en-elo-061.html","ezd-031":"en/ez/d-/03/en-ezd-031.html","ezd-030":"en/ez/d-/03/en-ezd-030.html","edd-089":"en/ed/d-/08/en-edd-089.html","edd-088":"en/ed/d-/08/en-edd-088.html","edgd-083":"en/ed/gd/-0/en-edgd-083.html","edgd-082":"en/ed/gd/-0/en-edgd-082.html","edgd-084":"en/ed/gd/-0/en-edgd-084.html","elo-048":"en/el/o-/04/en-elo-048.html","elo-047":"en/el/o-/04/en-elo-047.html","elo-050":"en/el/o-/05/en-elo-050.html","elo-052":"en/el/o-/05/en-elo-052.html","elo-054":"en/el/o-/05/en-elo-054.html","ezd-026":"en/ez/d-/02/en-ezd-026.html","edd-086":"en/ed/d-/08/en-edd-086.html","edgd-079":"en/ed/gd/-0/en-edgd-079.html","edgd-080":"en/ed/gd/-0/en-edgd-080.html","edgd-081":"en/ed/gd/-0/en-edgd-081.html","elo-042":"en/el/o-/04/en-elo-042.html","elo-041":"en/el/o-/04/en-elo-041.html","elo-039":"en/el/o-/03/en-elo-039.html","elo-038":"en/el/o-/03/en-elo-038.html","elo-037":"en/el/o-/03/en-elo-037.html","elo-044":"en/el/o-/04/en-elo-044.html","elo-043":"en/el/o-/04/en-elo-043.html","exd-052":"en/ex/d-/05/en-exd-052.html","ezd-023":"en/ez/d-/02/en-ezd-023.html","ezd-017":"en/ez/d-/01/en-ezd-017.html","ezd-021":"en/ez/d-/02/en-ezd-021.html","edd-083":"en/ed/d-/08/en-edd-083.html","exd-051":"en/ex/d-/05/en-exd-051.html","edd-085":"en/ed/d-/08/en-edd-085.html","edgd-076":"en/ed/gd/-0/en-edgd-076.html","edgd-078":"en/ed/gd/-0/en-edgd-078.html","elo-031":"en/el/o-/03/en-elo-031.html","elo-033":"en/el/o-/03/en-elo-033.html","elo-032":"en/el/o-/03/en-elo-032.html","elo-035":"en/el/o-/03/en-elo-035.html","elo-036":"en/el/o-/03/en-elo-036.html","elo-034":"en/el/o-/03/en-elo-034.html","ezd-016":"en/ez/d-/01/en-ezd-016.html","ezd-008":"en/ez/d-/00/en-ezd-008.html","ezd-010":"en/ez/d-/01/en-ezd-010.html","ezd-015":"en/ez/d-/01/en-ezd-015.html","edd-082":"en/ed/d-/08/en-edd-082.html","edgd-074":"en/ed/gd/-0/en-edgd-074.html","edgd-073":"en/ed/gd/-0/en-edgd-073.html","edgd-075":"en/ed/gd/-0/en-edgd-075.html","elo-026":"en/el/o-/02/en-elo-026.html","elo-027":"en/el/o-/02/en-elo-027.html","elo-025":"en/el/o-/02/en-elo-025.html","elo-029":"en/el/o-/02/en-elo-029.html","elo-028":"en/el/o-/02/en-elo-028.html","elo-030":"en/el/o-/03/en-elo-030.html","exd-059":"en/ex/d-/05/en-exd-059.html","ezd-013":"en/ez/d-/01/en-ezd-013.html","ezd-012":"en/ez/d-/01/en-ezd-012.html","exd-041":"en/ex/d-/04/en-exd-041.html","edd-081":"en/ed/d-/08/en-edd-081.html","edd-080":"en/ed/d-/08/en-edd-080.html","edgd-071":"en/ed/gd/-0/en-edgd-071.html","edgd-072":"en/ed/gd/-0/en-edgd-072.html","edgd-070":"en/ed/gd/-0/en-edgd-070.html","elo-019":"en/el/o-/01/en-elo-019.html","elo-021":"en/el/o-/02/en-elo-021.html","elo-020":"en/el/o-/02/en-elo-020.html","elo-022":"en/el/o-/02/en-elo-022.html","elo-024":"en/el/o-/02/en-elo-024.html","elo-023":"en/el/o-/02/en-elo-023.html","ezd-009":"en/ez/d-/00/en-ezd-009.html","edd-070":"en/ed/d-/07/en-edd-070.html","ezd-014":"en/ez/d-/01/en-ezd-014.html","edd-079":"en/ed/d-/07/en-edd-079.html","edd-078":"en/ed/d-/07/en-edd-078.html","ezd-011":"en/ez/d-/01/en-ezd-011.html","edgd-068":"en/ed/gd/-0/en-edgd-068.html","edgd-069":"en/ed/gd/-0/en-edgd-069.html","elo-016":"en/el/o-/01/en-elo-016.html","elo-015":"en/el/o-/01/en-elo-015.html","elo-008":"en/el/o-/00/en-elo-008.html","elo-010":"en/el/o-/01/en-elo-010.html","elo-009":"en/el/o-/00/en-elo-009.html","elo-007":"en/el/o-/00/en-elo-007.html","elo-012":"en/el/o-/01/en-elo-012.html","elo-011":"en/el/o-/01/en-elo-011.html","elo-006":"en/el/o-/00/en-elo-006.html","elo-002":"en/el/o-/00/en-elo-002.html","elo-001":"en/el/o-/00/en-elo-001.html","elo-003":"en/el/o-/00/en-elo-003.html","elo-004":"en/el/o-/00/en-elo-004.html","edd-077":"en/ed/d-/07/en-edd-077.html","edd-076":"en/ed/d-/07/en-edd-076.html","edgd-066":"en/ed/gd/-0/en-edgd-066.html","edd-074":"en/ed/d-/07/en-edd-074.html","edd-075":"en/ed/d-/07/en-edd-075.html","exd-050":"en/ex/d-/05/en-exd-050.html","edgd-064":"en/ed/gd/-0/en-edgd-064.html","edgd-065":"en/ed/gd/-0/en-edgd-065.html","edd-045":"en/ed/d-/04/en-edd-045.html","ezd-005":"en/ez/d-/00/en-ezd-005.html","ezd-007":"en/ez/d-/00/en-ezd-007.html","ezd-006":"en/ez/d-/00/en-ezd-006.html","ezd-004":"en/ez/d-/00/en-ezd-004.html","edd-073":"en/ed/d-/07/en-edd-073.html","ezd-003":"en/ez/d-/00/en-ezd-003.html","edd-072":"en/ed/d-/07/en-edd-072.html","edgd-060":"en/ed/gd/-0/en-edgd-060.html","edgd-061":"en/ed/gd/-0/en-edgd-061.html","edgd-062":"en/ed/gd/-0/en-edgd-062.html","exd-042":"en/ex/d-/04/en-exd-042.html","ezd-002":"en/ez/d-/00/en-ezd-002.html","edd-069":"en/ed/d-/06/en-edd-069.html","ezd-001":"en/ez/d-/00/en-ezd-001.html","eg-104":"en/eg/-1/04/en-eg-104.html","edgd-058":"en/ed/gd/-0/en-edgd-058.html","edgd-057":"en/ed/gd/-0/en-edgd-057.html","edgd-059":"en/ed/gd/-0/en-edgd-059.html","edd-065":"en/ed/d-/06/en-edd-065.html","edd-068":"en/ed/d-/06/en-edd-068.html","edd-067":"en/ed/d-/06/en-edd-067.html","edgd-055":"en/ed/gd/-0/en-edgd-055.html","edd-066":"en/ed/d-/06/en-edd-066.html","eg-105":"en/eg/-1/05/en-eg-105.html","edgd-052":"en/ed/gd/-0/en-edgd-052.html","edgd-051":"en/ed/gd/-0/en-edgd-051.html","edd-046":"en/ed/d-/04/en-edd-046.html","edgd-049":"en/ed/gd/-0/en-edgd-049.html","edgd-048":"en/ed/gd/-0/en-edgd-048.html","edgd-050":"en/ed/gd/-0/en-edgd-050.html","edd-043":"en/ed/d-/04/en-edd-043.html","eg-102":"en/eg/-1/02/en-eg-102.html","exd-060":"en/ex/d-/06/en-exd-060.html","edd-042":"en/ed/d-/04/en-edd-042.html","edgd-047":"en/ed/gd/-0/en-edgd-047.html","edgd-045":"en/ed/gd/-0/en-edgd-045.html","edd-049":"en/ed/d-/04/en-edd-049.html","edd-064":"en/ed/d-/06/en-edd-064.html","edd-063":"en/ed/d-/06/en-edd-063.html","edgd-043":"en/ed/gd/-0/en-edgd-043.html","edgd-042":"en/ed/gd/-0/en-edgd-042.html","edd-047":"en/ed/d-/04/en-edd-047.html","edd-048":"en/ed/d-/04/en-edd-048.html","edd-061":"en/ed/d-/06/en-edd-061.html","edd-062":"en/ed/d-/06/en-edd-062.html","edgd-041":"en/ed/gd/-0/en-edgd-041.html","edgd-040":"en/ed/gd/-0/en-edgd-040.html","edd-038":"en/ed/d-/03/en-edd-038.html","edgd-039":"en/ed/gd/-0/en-edgd-039.html","edd-057":"en/ed/d-/05/en-edd-057.html","edd-058":"en/ed/d-/05/en-edd-058.html","edd-039":"en/ed/d-/03/en-edd-039.html","edgd-036":"en/ed/gd/-0/en-edgd-036.html","edgd-037":"en/ed/gd/-0/en-edgd-037.html","exd-054":"en/ex/d-/05/en-exd-054.html","edd-041":"en/ed/d-/04/en-edd-041.html","edd-055":"en/ed/d-/05/en-edd-055.html","edd-056":"en/ed/d-/05/en-edd-056.html","edd-040":"en/ed/d-/04/en-edd-040.html","ek-101":"en/ek/-1/01/en-ek-101.html","exd-061":"en/ex/d-/06/en-exd-061.html","edd-037":"en/ed/d-/03/en-edd-037.html","exd-047":"en/ex/d-/04/en-exd-047.html","edd-054":"en/ed/d-/05/en-edd-054.html","edd-053":"en/ed/d-/05/en-edd-053.html","edd-036":"en/ed/d-/03/en-edd-036.html","edgd-033":"en/ed/gd/-0/en-edgd-033.html","edgd-032":"en/ed/gd/-0/en-edgd-032.html","exd-055":"en/ex/d-/05/en-exd-055.html","edd-035":"en/ed/d-/03/en-edd-035.html","edd-050":"en/ed/d-/05/en-edd-050.html","edd-052":"en/ed/d-/05/en-edd-052.html","edd-051":"en/ed/d-/05/en-edd-051.html","eh-101":"en/eh/-1/01/en-eh-101.html","edgd-028":"en/ed/gd/-0/en-edgd-028.html","edgd-027":"en/ed/gd/-0/en-edgd-027.html","edgd-026":"en/ed/gd/-0/en-edgd-026.html","exd-046":"en/ex/d-/04/en-exd-046.html","edgd-019":"en/ed/gd/-0/en-edgd-019.html","edgd-020":"en/ed/gd/-0/en-edgd-020.html","edgd-025":"en/ed/gd/-0/en-edgd-025.html","edgd-024":"en/ed/gd/-0/en-edgd-024.html","exd-045":"en/ex/d-/04/en-exd-045.html","edgd-016":"en/ed/gd/-0/en-edgd-016.html","edgd-017":"en/ed/gd/-0/en-edgd-017.html","edgd-015":"en/ed/gd/-0/en-edgd-015.html","edgd-014":"en/ed/gd/-0/en-edgd-014.html","edgd-012":"en/ed/gd/-0/en-edgd-012.html","edgd-013":"en/ed/gd/-0/en-edgd-013.html","edd-034":"en/ed/d-/03/en-edd-034.html","edd-033":"en/ed/d-/03/en-edd-033.html","edd-032":"en/ed/d-/03/en-edd-032.html","edd-030":"en/ed/d-/03/en-edd-030.html","edd-024":"en/ed/d-/02/en-edd-024.html","edd-017":"en/ed/d-/01/en-edd-017.html","edgd-008":"en/ed/gd/-0/en-edgd-008.html","edgd-004":"en/ed/gd/-0/en-edgd-004.html","edgd-003":"en/ed/gd/-0/en-edgd-003.html","evis-318":"en/ev/is/-3/en-evis-318.html","evis-317":"en/ev/is/-3/en-evis-317.html","eva-106":"en/ev/a-/10/en-eva-106.html","exw-006":"en/ex/w-/00/en-exw-006.html","eys-057":"en/ey/s-/05/en-eys-057.html","eva-107":"en/ev/a-/10/en-eva-107.html","emoi-022":"en/em/oi/-0/en-emoi-022.html","eva-108":"en/ev/a-/10/en-eva-108.html","ekw-062":"en/ek/w-/06/en-ekw-062.html","enki-028":"en/en/ki/-0/en-enki-028.html","embz-211":"en/em/bz/-2/en-embz-211.html","evis-319":"en/ev/is/-3/en-evis-319.html","eva-111":"en/ev/a-/11/en-eva-111.html","evis-320":"en/ev/is/-3/en-evis-320.html","eva-110":"en/ev/a-/11/en-eva-110.html","emoi-024":"en/em/oi/-0/en-emoi-024.html","eva-114":"en/ev/a-/11/en-eva-114.html","eva-115":"en/ev/a-/11/en-eva-115.html","etqr-160":"en/et/qr/-1/en-etqr-160.html","eva-116":"en/ev/a-/11/en-eva-116.html","eva-117":"en/ev/a-/11/en-eva-117.html","emot-012":"en/em/ot/-0/en-emot-012.html","emoi-016":"en/em/oi/-0/en-emoi-016.html","eva-118":"en/ev/a-/11/en-eva-118.html","eq-530":"en/eq/-5/30/en-eq-530.html","eq-529":"en/eq/-5/29/en-eq-529.html","eq-531":"en/eq/-5/31/en-eq-531.html","eva-119":"en/ev/a-/11/en-eva-119.html","eva-120":"en/ev/a-/12/en-eva-120.html","emois-011":"en/em/oi/s-/en-emois-011.html","ekdv-644":"en/ek/dv/-6/en-ekdv-644.html","ekdv-645":"en/ek/dv/-6/en-ekdv-645.html","ekdv-646":"en/ek/dv/-6/en-ekdv-646.html","etqr-162":"en/et/qr/-1/en-etqr-162.html","etqr-161":"en/et/qr/-1/en-etqr-161.html","emoi-027":"en/em/oi/-0/en-emoi-027.html","ebod-769":"en/eb/od/-7/en-ebod-769.html","ebod-770":"en/eb/od/-7/en-ebod-770.html","ebod-773":"en/eb/od/-7/en-ebod-773.html","ebod-768":"en/eb/od/-7/en-ebod-768.html","ebod-771":"en/eb/od/-7/en-ebod-771.html","eyan-159":"en/ey/an/-1/en-eyan-159.html","ebod-772":"en/eb/od/-7/en-ebod-772.html","ebod-774":"en/eb/od/-7/en-ebod-774.html","emoi-029":"en/em/oi/-0/en-emoi-029.html","emoi-025":"en/em/oi/-0/en-emoi-025.html","eva-109":"en/ev/a-/10/en-eva-109.html","endx-307":"en/en/dx/-3/en-endx-307.html","ewdx-321":"en/ew/dx/-3/en-ewdx-321.html","endx-308":"en/en/dx/-3/en-endx-308.html","ewdx-323":"en/ew/dx/-3/en-ewdx-323.html","ewdx-322":"en/ew/dx/-3/en-ewdx-322.html","evis-321":"en/ev/is/-3/en-evis-321.html","evis-322":"en/ev/is/-3/en-evis-322.html","ewdx-324":"en/ew/dx/-3/en-ewdx-324.html","endx-309":"en/en/dx/-3/en-endx-309.html","ewdx-326":"en/ew/dx/-3/en-ewdx-326.html","ewdx-325":"en/ew/dx/-3/en-ewdx-325.html","endx-310":"en/en/dx/-3/en-endx-310.html","ekai-018":"en/ek/ai/-0/en-ekai-018.html","enki-030":"en/en/ki/-0/en-enki-030.html","ecb-141":"en/ec/b-/14/en-ecb-141.html","ekw-063":"en/ek/w-/06/en-ekw-063.html","enki-029":"en/en/ki/-0/en-enki-029.html","ecb-140":"en/ec/b-/14/en-ecb-140.html","emoi-028":"en/em/oi/-0/en-emoi-028.html","endx-311":"en/en/dx/-3/en-endx-311.html","ewdx-329":"en/ew/dx/-3/en-ewdx-329.html","eys-058":"en/ey/s-/05/en-eys-058.html","etqr-163":"en/et/qr/-1/en-etqr-163.html","emoi-030":"en/em/oi/-0/en-emoi-030.html","euud-033":"en/eu/ud/-0/en-euud-033.html","eq-534":"en/eq/-5/34/en-eq-534.html","eq-532":"en/eq/-5/32/en-eq-532.html","eq-533":"en/eq/-5/33/en-eq-533.html","evis-323":"en/ev/is/-3/en-evis-323.html","embz-213":"en/em/bz/-2/en-embz-213.html","evis-324":"en/ev/is/-3/en-evis-324.html","emoi-026":"en/em/oi/-0/en-emoi-026.html","ekdv-647":"en/ek/dv/-6/en-ekdv-647.html","ekdv-648":"en/ek/dv/-6/en-ekdv-648.html","ekdv-649":"en/ek/dv/-6/en-ekdv-649.html","emoi-033":"en/em/oi/-0/en-emoi-033.html","emusu-001":"en/em/us/u-/en-emusu-001.html","exw-009":"en/ex/w-/00/en-exw-009.html","exw-012":"en/ex/w-/01/en-exw-012.html","emoi-035":"en/em/oi/-0/en-emoi-035.html","ebod-777":"en/eb/od/-7/en-ebod-777.html","ebod-776":"en/eb/od/-7/en-ebod-776.html","ebod-782":"en/eb/od/-7/en-ebod-782.html","ebod-778":"en/eb/od/-7/en-ebod-778.html","ebod-780":"en/eb/od/-7/en-ebod-780.html","ebod-783":"en/eb/od/-7/en-ebod-783.html","ebod-775":"en/eb/od/-7/en-ebod-775.html","ebod-781":"en/eb/od/-7/en-ebod-781.html","esk-316":"en/es/k-/31/en-esk-316.html","endx-312":"en/en/dx/-3/en-endx-312.html","endx-313":"en/en/dx/-3/en-endx-313.html","endx-316":"en/en/dx/-3/en-endx-316.html","endx-314":"en/en/dx/-3/en-endx-314.html","endx-315":"en/en/dx/-3/en-endx-315.html","ewdx-330":"en/ew/dx/-3/en-ewdx-330.html","emusu-002":"en/em/us/u-/en-emusu-002.html","eldx-071":"en/el/dx/-0/en-eldx-071.html","ewdx-331":"en/ew/dx/-3/en-ewdx-331.html","ewdx-332":"en/ew/dx/-3/en-ewdx-332.html","ewdx-333":"en/ew/dx/-3/en-ewdx-333.html","eldx-072":"en/el/dx/-0/en-eldx-072.html","etqr-164":"en/et/qr/-1/en-etqr-164.html","etqr-165":"en/et/qr/-1/en-etqr-165.html","eviz-065":"en/ev/iz/-0/en-eviz-065.html","evis-326":"en/ev/is/-3/en-evis-326.html","eldx-073":"en/el/dx/-0/en-eldx-073.html","ebvr-020":"en/eb/vr/-0/en-ebvr-020.html","eva-132":"en/ev/a-/13/en-eva-132.html","emoi-031":"en/em/oi/-0/en-emoi-031.html","eva-133":"en/ev/a-/13/en-eva-133.html","eva-134":"en/ev/a-/13/en-eva-134.html","emoi-034":"en/em/oi/-0/en-emoi-034.html","enkv-001":"en/en/kv/-0/en-enkv-001.html","emusu-003":"en/em/us/u-/en-emusu-003.html","ekai-019":"en/ek/ai/-0/en-ekai-019.html","eva-135":"en/ev/a-/13/en-eva-135.html","enki-031":"en/en/ki/-0/en-enki-031.html","ecb-142":"en/ec/b-/14/en-ecb-142.html","emoi-036":"en/em/oi/-0/en-emoi-036.html","ekw-064":"en/ek/w-/06/en-ekw-064.html","etqr-166":"en/et/qr/-1/en-etqr-166.html","evis-328":"en/ev/is/-3/en-evis-328.html","evis-327":"en/ev/is/-3/en-evis-327.html","embz-216":"en/em/bz/-2/en-embz-216.html","embz-215":"en/em/bz/-2/en-embz-215.html","eva-123":"en/ev/a-/12/en-eva-123.html","eviz-066":"en/ev/iz/-0/en-eviz-066.html","emois-014":"en/em/oi/s-/en-emois-014.html","emoi-032":"en/em/oi/-0/en-emoi-032.html","ekdv-651":"en/ek/dv/-6/en-ekdv-651.html","ekdv-650":"en/ek/dv/-6/en-ekdv-650.html","emoi-041":"en/em/oi/-0/en-emoi-041.html","exw-005":"en/ex/w-/00/en-exw-005.html","exw-008":"en/ex/w-/00/en-exw-008.html","exw-010":"en/ex/w-/01/en-exw-010.html","exw-014":"en/ex/w-/01/en-exw-014.html","etqr-168":"en/et/qr/-1/en-etqr-168.html","etqr-167":"en/et/qr/-1/en-etqr-167.html","eq-537":"en/eq/-5/37/en-eq-537.html","eq-536":"en/eq/-5/36/en-eq-536.html","emoi-039":"en/em/oi/-0/en-emoi-039.html","etqr-169":"en/et/qr/-1/en-etqr-169.html","ebod-785":"en/eb/od/-7/en-ebod-785.html","ebod-784":"en/eb/od/-7/en-ebod-784.html","ebod-788":"en/eb/od/-7/en-ebod-788.html","ebod-789":"en/eb/od/-7/en-ebod-789.html","ebod-786":"en/eb/od/-7/en-ebod-786.html","eyan-161":"en/ey/an/-1/en-eyan-161.html","ebod-787":"en/eb/od/-7/en-ebod-787.html","ebod-790":"en/eb/od/-7/en-ebod-790.html","eyan-160":"en/ey/an/-1/en-eyan-160.html","ebod-779":"en/eb/od/-7/en-ebod-779.html","emoi-042":"en/em/oi/-0/en-emoi-042.html","endx-321":"en/en/dx/-3/en-endx-321.html","endx-318":"en/en/dx/-3/en-endx-318.html","endx-319":"en/en/dx/-3/en-endx-319.html","endx-320":"en/en/dx/-3/en-endx-320.html","etqr-175":"en/et/qr/-1/en-etqr-175.html","etqr-177":"en/et/qr/-1/en-etqr-177.html","etqr-176":"en/et/qr/-1/en-etqr-176.html","etqr-171":"en/et/qr/-1/en-etqr-171.html","evis-330":"en/ev/is/-3/en-evis-330.html","etqr-170":"en/et/qr/-1/en-etqr-170.html","evis-329":"en/ev/is/-3/en-evis-329.html","enfd-5908":"en/en/fd/-5/en-enfd-5908.html","emoi-037":"en/em/oi/-0/en-emoi-037.html","ewdx-337":"en/ew/dx/-3/en-ewdx-337.html","ewdx-338":"en/ew/dx/-3/en-ewdx-338.html","ewdx-336":"en/ew/dx/-3/en-ewdx-336.html","ewdx-335":"en/ew/dx/-3/en-ewdx-335.html","eys-060":"en/ey/s-/06/en-eys-060.html","ewdx-334":"en/ew/dx/-3/en-ewdx-334.html","emois-016":"en/em/oi/s-/en-emois-016.html","eva-131":"en/ev/a-/13/en-eva-131.html","eva-121":"en/ev/a-/12/en-eva-121.html","eva-122":"en/ev/a-/12/en-eva-122.html","ekw-065":"en/ek/w-/06/en-ekw-065.html","eva-125":"en/ev/a-/12/en-eva-125.html","enki-032":"en/en/ki/-0/en-enki-032.html","etqr-186":"en/et/qr/-1/en-etqr-186.html","etqr-185":"en/et/qr/-1/en-etqr-185.html","etqr-183":"en/et/qr/-1/en-etqr-183.html","etqr-182":"en/et/qr/-1/en-etqr-182.html","etqr-184":"en/et/qr/-1/en-etqr-184.html","etqr-180":"en/et/qr/-1/en-etqr-180.html","etqr-181":"en/et/qr/-1/en-etqr-181.html","ecb-143":"en/ec/b-/14/en-ecb-143.html","eva-127":"en/ev/a-/12/en-eva-127.html","evis-331":"en/ev/is/-3/en-evis-331.html","eviz-067":"en/ev/iz/-0/en-eviz-067.html","eva-128":"en/ev/a-/12/en-eva-128.html","embz-218":"en/em/bz/-2/en-embz-218.html","etqr-179":"en/et/qr/-1/en-etqr-179.html","etqr-178":"en/et/qr/-1/en-etqr-178.html","euud-034":"en/eu/ud/-0/en-euud-034.html","ekdv-652":"en/ek/dv/-6/en-ekdv-652.html","emot-013":"en/em/ot/-0/en-emot-013.html","enfd-4334":"en/en/fd/-4/en-enfd-4334.html","emoi-040":"en/em/oi/-0/en-emoi-040.html","eq-540":"en/eq/-5/40/en-eq-540.html","etqr-187":"en/et/qr/-1/en-etqr-187.html","eq-539":"en/eq/-5/39/en-eq-539.html","eq-538":"en/eq/-5/38/en-eq-538.html","ebod-798":"en/eb/od/-7/en-ebod-798.html","ebod-795":"en/eb/od/-7/en-ebod-795.html","ebod-791":"en/eb/od/-7/en-ebod-791.html","ebod-797":"en/eb/od/-7/en-ebod-797.html","ebod-792":"en/eb/od/-7/en-ebod-792.html","eyan-162":"en/ey/an/-1/en-eyan-162.html","ebod-796":"en/eb/od/-7/en-ebod-796.html","ebod-794":"en/eb/od/-7/en-ebod-794.html","ebod-793":"en/eb/od/-7/en-ebod-793.html","emoi-038":"en/em/oi/-0/en-emoi-038.html","emoi-043":"en/em/oi/-0/en-emoi-043.html","ekdv-653":"en/ek/dv/-6/en-ekdv-653.html","eva-124":"en/ev/a-/12/en-eva-124.html","eva-126":"en/ev/a-/12/en-eva-126.html","eva-129":"en/ev/a-/12/en-eva-129.html","eva-130":"en/ev/a-/13/en-eva-130.html","evis-332":"en/ev/is/-3/en-evis-332.html","evis-333":"en/ev/is/-3/en-evis-333.html","emoi-045":"en/em/oi/-0/en-emoi-045.html","eih-057":"en/ei/h-/05/en-eih-057.html","ewdx-340":"en/ew/dx/-3/en-ewdx-340.html","ewdx-339":"en/ew/dx/-3/en-ewdx-339.html","ewdx-341":"en/ew/dx/-3/en-ewdx-341.html","ewdx-342":"en/ew/dx/-3/en-ewdx-342.html","ewdx-343":"en/ew/dx/-3/en-ewdx-343.html","ewdx-344":"en/ew/dx/-3/en-ewdx-344.html","ewdx-346":"en/ew/dx/-3/en-ewdx-346.html","ewdx-345":"en/ew/dx/-3/en-ewdx-345.html","endx-322":"en/en/dx/-3/en-endx-322.html","endx-323":"en/en/dx/-3/en-endx-323.html","endx-324":"en/en/dx/-3/en-endx-324.html","ekw-066":"en/ek/w-/06/en-ekw-066.html","endx-325":"en/en/dx/-3/en-endx-325.html","endx-326":"en/en/dx/-3/en-endx-326.html","etqr-190":"en/et/qr/-1/en-etqr-190.html","etqr-189":"en/et/qr/-1/en-etqr-189.html","eiki-098":"en/ei/ki/-0/en-eiki-098.html","eys-061":"en/ey/s-/06/en-eys-061.html","etef-005":"en/et/ef/-0/en-etef-005.html","etqr-188":"en/et/qr/-1/en-etqr-188.html","enkv-002":"en/en/kv/-0/en-enkv-002.html","emoi-044":"en/em/oi/-0/en-emoi-044.html","enki-033":"en/en/ki/-0/en-enki-033.html","embz-219":"en/em/bz/-2/en-embz-219.html","evis-334":"en/ev/is/-3/en-evis-334.html","evis-335":"en/ev/is/-3/en-evis-335.html","embz-220":"en/em/bz/-2/en-embz-220.html","eviz-069":"en/ev/iz/-0/en-eviz-069.html","emot-014":"en/em/ot/-0/en-emot-014.html","ekdv-654":"en/ek/dv/-6/en-ekdv-654.html","exw-021":"en/ex/w-/02/en-exw-021.html","etqr-191":"en/et/qr/-1/en-etqr-191.html","etqr-192":"en/et/qr/-1/en-etqr-192.html","etqr-193":"en/et/qr/-1/en-etqr-193.html","etqr-194":"en/et/qr/-1/en-etqr-194.html","etqr-195":"en/et/qr/-1/en-etqr-195.html","etqr-196":"en/et/qr/-1/en-etqr-196.html","ebod-803":"en/eb/od/-8/en-ebod-803.html","ebod-804":"en/eb/od/-8/en-ebod-804.html","ebod-805":"en/eb/od/-8/en-ebod-805.html","eyan-163":"en/ey/an/-1/en-eyan-163.html","ebod-800":"en/eb/od/-8/en-ebod-800.html","ebod-799":"en/eb/od/-7/en-ebod-799.html","ebod-801":"en/eb/od/-8/en-ebod-801.html","ebod-802":"en/eb/od/-8/en-ebod-802.html","eyan-164":"en/ey/an/-1/en-eyan-164.html","etqr-198":"en/et/qr/-1/en-etqr-198.html","etqr-197":"en/et/qr/-1/en-etqr-197.html","ekdv-655":"en/ek/dv/-6/en-ekdv-655.html","evis-336":"en/ev/is/-3/en-evis-336.html","evis-337":"en/ev/is/-3/en-evis-337.html","ekw-067":"en/ek/w-/06/en-ekw-067.html","ekai-020":"en/ek/ai/-0/en-ekai-020.html","eys-062":"en/ey/s-/06/en-eys-062.html","eva-139":"en/ev/a-/13/en-eva-139.html","eva-136":"en/ev/a-/13/en-eva-136.html","ello-001":"en/el/lo/-0/en-ello-001.html","ello-002":"en/el/lo/-0/en-ello-002.html","etqr-202":"en/et/qr/-2/en-etqr-202.html","etqr-203":"en/et/qr/-2/en-etqr-203.html","enki-034":"en/en/ki/-0/en-enki-034.html","etqr-200":"en/et/qr/-2/en-etqr-200.html","etqr-201":"en/et/qr/-2/en-etqr-201.html","etqr-199":"en/et/qr/-1/en-etqr-199.html","embz-221":"en/em/bz/-2/en-embz-221.html","evis-338":"en/ev/is/-3/en-evis-338.html","evis-339":"en/ev/is/-3/en-evis-339.html","embz-222":"en/em/bz/-2/en-embz-222.html","evis-340":"en/ev/is/-3/en-evis-340.html","emot-015":"en/em/ot/-0/en-emot-015.html","etqr-204":"en/et/qr/-2/en-etqr-204.html","ebod-806":"en/eb/od/-8/en-ebod-806.html","ebod-811":"en/eb/od/-8/en-ebod-811.html","ebod-810":"en/eb/od/-8/en-ebod-810.html","ebod-807":"en/eb/od/-8/en-ebod-807.html","ebod-808":"en/eb/od/-8/en-ebod-808.html","ebod-812":"en/eb/od/-8/en-ebod-812.html","eyan-165":"en/ey/an/-1/en-eyan-165.html","ebod-809":"en/eb/od/-8/en-ebod-809.html","eyan-166":"en/ey/an/-1/en-eyan-166.html","ekdv-657":"en/ek/dv/-6/en-ekdv-657.html","endx-332":"en/en/dx/-3/en-endx-332.html","endx-333":"en/en/dx/-3/en-endx-333.html","endx-334":"en/en/dx/-3/en-endx-334.html","endx-335":"en/en/dx/-3/en-endx-335.html","ewdx-353":"en/ew/dx/-3/en-ewdx-353.html","etqr-211":"en/et/qr/-2/en-etqr-211.html","etqr-209":"en/et/qr/-2/en-etqr-209.html","etqr-210":"en/et/qr/-2/en-etqr-210.html","etqr-208":"en/et/qr/-2/en-etqr-208.html","etqr-207":"en/et/qr/-2/en-etqr-207.html","etqr-206":"en/et/qr/-2/en-etqr-206.html","etqr-205":"en/et/qr/-2/en-etqr-205.html","ewdx-352":"en/ew/dx/-3/en-ewdx-352.html","ewdx-351":"en/ew/dx/-3/en-ewdx-351.html","ewdx-350":"en/ew/dx/-3/en-ewdx-350.html","ewdx-349":"en/ew/dx/-3/en-ewdx-349.html","evis-343":"en/ev/is/-3/en-evis-343.html","ewdx-348":"en/ew/dx/-3/en-ewdx-348.html","evis-341":"en/ev/is/-3/en-evis-341.html","evis-342":"en/ev/is/-3/en-evis-342.html","ello-004":"en/el/lo/-0/en-ello-004.html","exmu-062":"en/ex/mu/-0/en-exmu-062.html","ello-003":"en/el/lo/-0/en-ello-003.html","enki-035":"en/en/ki/-0/en-enki-035.html","ekai-021":"en/ek/ai/-0/en-ekai-021.html","ekw-068":"en/ek/w-/06/en-ekw-068.html","ecb-144":"en/ec/b-/14/en-ecb-144.html","evis-345":"en/ev/is/-3/en-evis-345.html","evis-346":"en/ev/is/-3/en-evis-346.html","emot-016":"en/em/ot/-0/en-emot-016.html","exw-026":"en/ex/w-/02/en-exw-026.html","exw-017":"en/ex/w-/01/en-exw-017.html","exw-023":"en/ex/w-/02/en-exw-023.html","emst-001":"en/em/st/-0/en-emst-001.html","emusu-004":"en/em/us/u-/en-emusu-004.html","ebod-814":"en/eb/od/-8/en-ebod-814.html","ebod-816":"en/eb/od/-8/en-ebod-816.html","ebod-818":"en/eb/od/-8/en-ebod-818.html","ebod-815":"en/eb/od/-8/en-ebod-815.html","ebod-819":"en/eb/od/-8/en-ebod-819.html","ebod-813":"en/eb/od/-8/en-ebod-813.html","eyan-168":"en/ey/an/-1/en-eyan-168.html","eyan-169":"en/ey/an/-1/en-eyan-169.html","eyan-167":"en/ey/an/-1/en-eyan-167.html","ebod-817":"en/eb/od/-8/en-ebod-817.html","ekdv-658":"en/ek/dv/-6/en-ekdv-658.html","ekdv-659":"en/ek/dv/-6/en-ekdv-659.html","ewdx-354":"en/ew/dx/-3/en-ewdx-354.html","ewdx-356":"en/ew/dx/-3/en-ewdx-356.html","ewdx-355":"en/ew/dx/-3/en-ewdx-355.html","ewdx-357":"en/ew/dx/-3/en-ewdx-357.html","exmu-063":"en/ex/mu/-0/en-exmu-063.html","eva-150":"en/ev/a-/15/en-eva-150.html","evis-347":"en/ev/is/-3/en-evis-347.html","endx-339":"en/en/dx/-3/en-endx-339.html","eva-157":"en/ev/a-/15/en-eva-157.html","emlb-032":"en/em/lb/-0/en-emlb-032.html","enki-036":"en/en/ki/-0/en-enki-036.html","eys-064":"en/ey/s-/06/en-eys-064.html","eva-158":"en/ev/a-/15/en-eva-158.html","ekw-069":"en/ek/w-/06/en-ekw-069.html","embz-226":"en/em/bz/-2/en-embz-226.html","evis-349":"en/ev/is/-3/en-evis-349.html","embz-225":"en/em/bz/-2/en-embz-225.html","eva-160":"en/ev/a-/16/en-eva-160.html","etqr-221":"en/et/qr/-2/en-etqr-221.html","etqr-223":"en/et/qr/-2/en-etqr-223.html","etqr-225":"en/et/qr/-2/en-etqr-225.html","etqr-224":"en/et/qr/-2/en-etqr-224.html","etqr-219":"en/et/qr/-2/en-etqr-219.html","etqr-220":"en/et/qr/-2/en-etqr-220.html","etw-006":"en/et/w-/00/en-etw-006.html","ebod-821":"en/eb/od/-8/en-ebod-821.html","ebod-823":"en/eb/od/-8/en-ebod-823.html","ebod-825":"en/eb/od/-8/en-ebod-825.html","ebod-826":"en/eb/od/-8/en-ebod-826.html","ebod-820":"en/eb/od/-8/en-ebod-820.html","ebod-824":"en/eb/od/-8/en-ebod-824.html","ebod-822":"en/eb/od/-8/en-ebod-822.html","ebod-827":"en/eb/od/-8/en-ebod-827.html","ekdv-660":"en/ek/dv/-6/en-ekdv-660.html","ello-008":"en/el/lo/-0/en-ello-008.html","exmu-064":"en/ex/mu/-0/en-exmu-064.html","endx-345":"en/en/dx/-3/en-endx-345.html","endx-341":"en/en/dx/-3/en-endx-341.html","endx-342":"en/en/dx/-3/en-endx-342.html","endx-343":"en/en/dx/-3/en-endx-343.html","endx-344":"en/en/dx/-3/en-endx-344.html","evis-352":"en/ev/is/-3/en-evis-352.html","erk-001":"en/er/k-/00/en-erk-001.html","ewdx-362":"en/ew/dx/-3/en-ewdx-362.html","ewdx-358":"en/ew/dx/-3/en-ewdx-358.html","ewdx-359":"en/ew/dx/-3/en-ewdx-359.html","ewdx-361":"en/ew/dx/-3/en-ewdx-361.html","ewdx-360":"en/ew/dx/-3/en-ewdx-360.html","emlb-033":"en/em/lb/-0/en-emlb-033.html","enki-037":"en/en/ki/-0/en-enki-037.html","emst-003":"en/em/st/-0/en-emst-003.html","ekw-070":"en/ek/w-/07/en-ekw-070.html","ecb-145":"en/ec/b-/14/en-ecb-145.html","embz-228":"en/em/bz/-2/en-embz-228.html","evis-356":"en/ev/is/-3/en-evis-356.html","embz-227":"en/em/bz/-2/en-embz-227.html","etqr-243":"en/et/qr/-2/en-etqr-243.html","etqr-242":"en/et/qr/-2/en-etqr-242.html","eva-144":"en/ev/a-/14/en-eva-144.html","eva-156":"en/ev/a-/15/en-eva-156.html","eva-162":"en/ev/a-/16/en-eva-162.html","erk-002":"en/er/k-/00/en-erk-002.html","ebod-831":"en/eb/od/-8/en-ebod-831.html","ebod-829":"en/eb/od/-8/en-ebod-829.html","ebod-830":"en/eb/od/-8/en-ebod-830.html","ebod-828":"en/eb/od/-8/en-ebod-828.html","ebod-833":"en/eb/od/-8/en-ebod-833.html","ebod-835":"en/eb/od/-8/en-ebod-835.html","eyan-170":"en/ey/an/-1/en-eyan-170.html","ebod-834":"en/eb/od/-8/en-ebod-834.html","ebod-832":"en/eb/od/-8/en-ebod-832.html","ekdv-661":"en/ek/dv/-6/en-ekdv-661.html","emst-002":"en/em/st/-0/en-emst-002.html","erk-003":"en/er/k-/00/en-erk-003.html","etqr-248":"en/et/qr/-2/en-etqr-248.html","etqr-249":"en/et/qr/-2/en-etqr-249.html","etqr-250":"en/et/qr/-2/en-etqr-250.html","etqr-245":"en/et/qr/-2/en-etqr-245.html","etqr-246":"en/et/qr/-2/en-etqr-246.html","etqr-247":"en/et/qr/-2/en-etqr-247.html","etqr-244":"en/et/qr/-2/en-etqr-244.html","evis-358":"en/ev/is/-3/en-evis-358.html","evis-357":"en/ev/is/-3/en-evis-357.html","evis-359":"en/ev/is/-3/en-evis-359.html","enki-038":"en/en/ki/-0/en-enki-038.html","eys-066":"en/ey/s-/06/en-eys-066.html","erk-004":"en/er/k-/00/en-erk-004.html","ekw-071":"en/ek/w-/07/en-ekw-071.html","ecb-146":"en/ec/b-/14/en-ecb-146.html","embz-229":"en/em/bz/-2/en-embz-229.html","eviz-070":"en/ev/iz/-0/en-eviz-070.html","evis-360":"en/ev/is/-3/en-evis-360.html","evis-361":"en/ev/is/-3/en-evis-361.html","erk-005":"en/er/k-/00/en-erk-005.html","ebod-837":"en/eb/od/-8/en-ebod-837.html","ebod-836":"en/eb/od/-8/en-ebod-836.html","ebod-843":"en/eb/od/-8/en-ebod-843.html","ebod-841":"en/eb/od/-8/en-ebod-841.html","ebod-844":"en/eb/od/-8/en-ebod-844.html","ebod-840":"en/eb/od/-8/en-ebod-840.html","ebod-845":"en/eb/od/-8/en-ebod-845.html","ebod-842":"en/eb/od/-8/en-ebod-842.html","exmu-068":"en/ex/mu/-0/en-exmu-068.html","ebod-838":"en/eb/od/-8/en-ebod-838.html","ebod-839":"en/eb/od/-8/en-ebod-839.html","ekdv-662":"en/ek/dv/-6/en-ekdv-662.html","ekdv-663":"en/ek/dv/-6/en-ekdv-663.html","eva-152":"en/ev/a-/15/en-eva-152.html","erk-006":"en/er/k-/00/en-erk-006.html","evis-363":"en/ev/is/-3/en-evis-363.html","evis-364":"en/ev/is/-3/en-evis-364.html","evis-362":"en/ev/is/-3/en-evis-362.html","emaz-393":"en/em/az/-3/en-emaz-393.html","eva-161":"en/ev/a-/16/en-eva-161.html","etqr-257":"en/et/qr/-2/en-etqr-257.html","enki-039":"en/en/ki/-0/en-enki-039.html","eys-067":"en/ey/s-/06/en-eys-067.html","exmu-065":"en/ex/mu/-0/en-exmu-065.html","embz-232":"en/em/bz/-2/en-embz-232.html","evis-365":"en/ev/is/-3/en-evis-365.html","embz-231":"en/em/bz/-2/en-embz-231.html","ekw-072":"en/ek/w-/07/en-ekw-072.html","ek-003":"en/ek/-0/03/en-ek-003.html","ebod-849":"en/eb/od/-8/en-ebod-849.html","ebod-846":"en/eb/od/-8/en-ebod-846.html","ebod-847":"en/eb/od/-8/en-ebod-847.html","eyan-172":"en/ey/an/-1/en-eyan-172.html","ebod-852":"en/eb/od/-8/en-ebod-852.html","ebod-851":"en/eb/od/-8/en-ebod-851.html","eyan-171":"en/ey/an/-1/en-eyan-171.html","ebod-850":"en/eb/od/-8/en-ebod-850.html","ebod-848":"en/eb/od/-8/en-ebod-848.html","ekdv-665":"en/ek/dv/-6/en-ekdv-665.html","erht-002":"en/er/ht/-0/en-erht-002.html","ebvr-052":"en/eb/vr/-0/en-ebvr-052.html","etqr-269":"en/et/qr/-2/en-etqr-269.html","exmu-067":"en/ex/mu/-0/en-exmu-067.html","evis-368":"en/ev/is/-3/en-evis-368.html","evis-366":"en/ev/is/-3/en-evis-366.html","evis-367":"en/ev/is/-3/en-evis-367.html","etqr-271":"en/et/qr/-2/en-etqr-271.html","etqr-270":"en/et/qr/-2/en-etqr-270.html","exmu-066":"en/ex/mu/-0/en-exmu-066.html","ekdv-664":"en/ek/dv/-6/en-ekdv-664.html","enki-040":"en/en/ki/-0/en-enki-040.html","eys-068":"en/ey/s-/06/en-eys-068.html","exw-020":"en/ex/w-/02/en-exw-020.html","exw-022":"en/ex/w-/02/en-exw-022.html","exw-027":"en/ex/w-/02/en-exw-027.html","ekw-073":"en/ek/w-/07/en-ekw-073.html","eiki-101":"en/ei/ki/-1/en-eiki-101.html","embz-234":"en/em/bz/-2/en-embz-234.html","embz-233":"en/em/bz/-2/en-embz-233.html","evis-369":"en/ev/is/-3/en-evis-369.html","eviz-071":"en/ev/iz/-0/en-eviz-071.html","erk-007":"en/er/k-/00/en-erk-007.html","ekdv-666":"en/ek/dv/-6/en-ekdv-666.html","erk-008":"en/er/k-/00/en-erk-008.html","exmu-069":"en/ex/mu/-0/en-exmu-069.html","ebod-857":"en/eb/od/-8/en-ebod-857.html","ebod-853":"en/eb/od/-8/en-ebod-853.html","ebod-854":"en/eb/od/-8/en-ebod-854.html","eyan-176":"en/ey/an/-1/en-eyan-176.html","eyan-174":"en/ey/an/-1/en-eyan-174.html","eyan-173":"en/ey/an/-1/en-eyan-173.html","ebod-855":"en/eb/od/-8/en-ebod-855.html","eyan-175":"en/ey/an/-1/en-eyan-175.html","ebod-856":"en/eb/od/-8/en-ebod-856.html","evis-371":"en/ev/is/-3/en-evis-371.html","evis-370":"en/ev/is/-3/en-evis-370.html","exmu-071":"en/ex/mu/-0/en-exmu-071.html","ekbe-004":"en/ek/be/-0/en-ekbe-004.html","ecb-147":"en/ec/b-/14/en-ecb-147.html","enki-041":"en/en/ki/-0/en-enki-041.html","etqr-289":"en/et/qr/-2/en-etqr-289.html","etqr-288":"en/et/qr/-2/en-etqr-288.html","etqr-287":"en/et/qr/-2/en-etqr-287.html","erk-010":"en/er/k-/01/en-erk-010.html","embz-236":"en/em/bz/-2/en-embz-236.html","evis-374":"en/ev/is/-3/en-evis-374.html","evis-372":"en/ev/is/-3/en-evis-372.html","embz-235":"en/em/bz/-2/en-embz-235.html","evis-373":"en/ev/is/-3/en-evis-373.html","erk-009":"en/er/k-/00/en-erk-009.html","erof-001":"en/er/of/-0/en-erof-001.html","ekdv-667":"en/ek/dv/-6/en-ekdv-667.html","ekdv-668":"en/ek/dv/-6/en-ekdv-668.html","erht-006":"en/er/ht/-0/en-erht-006.html","erht-005":"en/er/ht/-0/en-erht-005.html","erk-012":"en/er/k-/01/en-erk-012.html","erof-002":"en/er/of/-0/en-erof-002.html","ebod-864":"en/eb/od/-8/en-ebod-864.html","ebod-862":"en/eb/od/-8/en-ebod-862.html","ebod-865":"en/eb/od/-8/en-ebod-865.html","ebod-858":"en/eb/od/-8/en-ebod-858.html","eyan-178":"en/ey/an/-1/en-eyan-178.html","ebod-860":"en/eb/od/-8/en-ebod-860.html","ebod-863":"en/eb/od/-8/en-ebod-863.html","ebod-861":"en/eb/od/-8/en-ebod-861.html","eyan-177":"en/ey/an/-1/en-eyan-177.html","ebod-859":"en/eb/od/-8/en-ebod-859.html","evis-375":"en/ev/is/-3/en-evis-375.html","erof-003":"en/er/of/-0/en-erof-003.html","exmu-072":"en/ex/mu/-0/en-exmu-072.html","ensr-001":"en/en/sr/-0/en-ensr-001.html","ekw-074":"en/ek/w-/07/en-ekw-074.html","enki-042":"en/en/ki/-0/en-enki-042.html","eys-070":"en/ey/s-/07/en-eys-070.html","ensr-002":"en/en/sr/-0/en-ensr-002.html","erk-013":"en/er/k-/01/en-erk-013.html","etqr-298":"en/et/qr/-2/en-etqr-298.html","etqr-297":"en/et/qr/-2/en-etqr-297.html","etqr-299":"en/et/qr/-2/en-etqr-299.html","etqr-300":"en/et/qr/-3/en-etqr-300.html","etqr-301":"en/et/qr/-3/en-etqr-301.html","etqr-303":"en/et/qr/-3/en-etqr-303.html","etqr-304":"en/et/qr/-3/en-etqr-304.html","etqr-302":"en/et/qr/-3/en-etqr-302.html","erof-004":"en/er/of/-0/en-erof-004.html","embz-238":"en/em/bz/-2/en-embz-238.html","evis-376":"en/ev/is/-3/en-evis-376.html","evis-377":"en/ev/is/-3/en-evis-377.html","embz-237":"en/em/bz/-2/en-embz-237.html","emot-017":"en/em/ot/-0/en-emot-017.html","erof-005":"en/er/of/-0/en-erof-005.html","euud-035":"en/eu/ud/-0/en-euud-035.html","egfj-002":"en/eg/fj/-0/en-egfj-002.html","ekdv-670":"en/ek/dv/-6/en-ekdv-670.html","ekdv-669":"en/ek/dv/-6/en-ekdv-669.html","etqr-307":"en/et/qr/-3/en-etqr-307.html","etqr-308":"en/et/qr/-3/en-etqr-308.html","etqr-306":"en/et/qr/-3/en-etqr-306.html","etqr-305":"en/et/qr/-3/en-etqr-305.html","exmo-005":"en/ex/mo/-0/en-exmo-005.html","erof-006":"en/er/of/-0/en-erof-006.html","erht-007":"en/er/ht/-0/en-erht-007.html","erht-008":"en/er/ht/-0/en-erht-008.html","ebod-871":"en/eb/od/-8/en-ebod-871.html","ebod-870":"en/eb/od/-8/en-ebod-870.html","ebod-869":"en/eb/od/-8/en-ebod-869.html","ebod-867":"en/eb/od/-8/en-ebod-867.html","ebod-866":"en/eb/od/-8/en-ebod-866.html","ebod-872":"en/eb/od/-8/en-ebod-872.html","ebod-868":"en/eb/od/-8/en-ebod-868.html","eyan-179":"en/ey/an/-1/en-eyan-179.html","evis-380":"en/ev/is/-3/en-evis-380.html","evis-378":"en/ev/is/-3/en-evis-378.html","evis-379":"en/ev/is/-3/en-evis-379.html","erof-007":"en/er/of/-0/en-erof-007.html","exmu-073":"en/ex/mu/-0/en-exmu-073.html"}